{"actualizado":"2026-06-24T16:42:02.7020996Z","pedidos":[{"OC":"OC-207-1503","Producto":"ROLL ON WILL COUNTY 75ML","Code":"10-01","Total Unds":144.0,"Total Cajas":0.75,"Status":"Entregado","Fecha de Pedido":"2026-06-12","Fecha de Entrega":"2026-06-18","Cliente":"VARIEDADES DE TODO PARA MICASA SOCIEDAD ANONIMA VARIEDADES DE TODO PARA MI CASA","Cod Cliente":"207","Peso Volumetrico":0.02775},{"OC":"OC-207-1503","Producto":"ROLL ON BLACK SOFT 75ML","Code":"10-03","Total Unds":240.0,"Total Cajas":1.25,"Status":"Entregado","Fecha de Pedido":"2026-06-12","Fecha de Entrega":"2026-06-18","Cliente":"VARIEDADES DE TODO PARA MICASA SOCIEDAD ANONIMA VARIEDADES DE TODO PARA MI CASA","Cod Cliente":"207","Peso Volumetrico":0.04625},{"OC":"OC-207-1503","Producto":"ROLL ON MUSK NARANJA 75ML","Code":"10-07","Total Unds":240.0,"Total Cajas":1.25,"Status":"Entregado","Fecha de Pedido":"2026-06-12","Fecha de Entrega":"2026-06-18","Cliente":"VARIEDADES DE TODO PARA MICASA SOCIEDAD ANONIMA VARIEDADES DE TODO PARA MI CASA","Cod Cliente":"207","Peso Volumetrico":0.04625},{"OC":"OC-207-1503","Producto":"ROLL ON PARIS DACKAR 75ML","Code":"10-10","Total Unds":240.0,"Total Cajas":1.25,"Status":"Entregado","Fecha de Pedido":"2026-06-12","Fecha de Entrega":"2026-06-18","Cliente":"VARIEDADES DE TODO PARA MICASA SOCIEDAD ANONIMA VARIEDADES DE TODO PARA MI CASA","Cod Cliente":"207","Peso Volumetrico":0.04625},{"OC":"OC-207-1503","Producto":"ROLL ON TRIUNFO 75ML","Code":"10-16","Total Unds":240.0,"Total Cajas":1.25,"Status":"Entregado","Fecha de Pedido":"2026-06-12","Fecha de Entrega":"2026-06-18","Cliente":"VARIEDADES DE TODO PARA MICASA SOCIEDAD ANONIMA VARIEDADES DE TODO PARA MI CASA","Cod Cliente":"207","Peso Volumetrico":0.04625},{"OC":"OC-207-1503","Producto":"ROLL ON ROSE MEN 75ML","Code":"10-19","Total Unds":168.0,"Total Cajas":0.875,"Status":"Entregado","Fecha de Pedido":"2026-06-12","Fecha de Entrega":"2026-06-18","Cliente":"VARIEDADES DE TODO PARA MICASA SOCIEDAD ANONIMA VARIEDADES DE TODO PARA MI CASA","Cod Cliente":"207","Peso Volumetrico":0.032375},{"OC":"OC-207-1503","Producto":"ROLL ON SWEET HONEY 75ML","Code":"10-02","Total Unds":144.0,"Total Cajas":0.75,"Status":"Entregado","Fecha de Pedido":"2026-06-12","Fecha de Entrega":"2026-06-18","Cliente":"VARIEDADES DE TODO PARA MICASA SOCIEDAD ANONIMA VARIEDADES DE TODO PARA MI CASA","Cod Cliente":"207","Peso Volumetrico":0.02775},{"OC":"OC-207-1503","Producto":"ROLL ON FARM AWAY 75ML","Code":"10-08","Total Unds":144.0,"Total Cajas":0.75,"Status":"Entregado","Fecha de Pedido":"2026-06-12","Fecha de Entrega":"2026-06-18","Cliente":"VARIEDADES DE TODO PARA MICASA SOCIEDAD ANONIMA VARIEDADES DE TODO PARA MI CASA","Cod Cliente":"207","Peso Volumetrico":0.02775},{"OC":"OC-207-1503","Producto":"ROLL ON FIEL 75ML","Code":"10-09","Total Unds":144.0,"Total Cajas":0.75,"Status":"Entregado","Fecha de Pedido":"2026-06-12","Fecha de Entrega":"2026-06-18","Cliente":"VARIEDADES DE TODO PARA MICASA SOCIEDAD ANONIMA VARIEDADES DE TODO PARA MI CASA","Cod Cliente":"207","Peso Volumetrico":0.02775},{"OC":"OC-207-1503","Producto":"ROLL ON CANDY 75ML","Code":"10-11","Total Unds":144.0,"Total Cajas":0.75,"Status":"Entregado","Fecha de Pedido":"2026-06-12","Fecha de Entrega":"2026-06-18","Cliente":"VARIEDADES DE TODO PARA MICASA SOCIEDAD ANONIMA VARIEDADES DE TODO PARA MI CASA","Cod Cliente":"207","Peso Volumetrico":0.02775},{"OC":"OC-207-1503","Producto":"ROLL ON IMARY 75ML","Code":"10-12","Total Unds":144.0,"Total Cajas":0.75,"Status":"Entregado","Fecha de Pedido":"2026-06-12","Fecha de Entrega":"2026-06-18","Cliente":"VARIEDADES DE TODO PARA MICASA SOCIEDAD ANONIMA VARIEDADES DE TODO PARA MI CASA","Cod Cliente":"207","Peso Volumetrico":0.02775},{"OC":"OC-207-1503","Producto":"ROLL ON INDIRA 75ML","Code":"10-18","Total Unds":144.0,"Total Cajas":0.75,"Status":"Entregado","Fecha de Pedido":"2026-06-12","Fecha de Entrega":"2026-06-18","Cliente":"VARIEDADES DE TODO PARA MICASA SOCIEDAD ANONIMA VARIEDADES DE TODO PARA MI CASA","Cod Cliente":"207","Peso Volumetrico":0.02775},{"OC":"OC-207-1503","Producto":"ROLL ON WILL COUNTY 50ML","Code":"10-20","Total Unds":336.0,"Total Cajas":1.23529411764706,"Status":"Entregado","Fecha de Pedido":"2026-06-12","Fecha de Entrega":"2026-06-18","Cliente":"VARIEDADES DE TODO PARA MICASA SOCIEDAD ANONIMA VARIEDADES DE TODO PARA MI CASA","Cod Cliente":"207","Peso Volumetrico":0.0457058823529412},{"OC":"OC-207-1503","Producto":"ROLL ON BLACK SOFT 50ML","Code":"10-21","Total Unds":336.0,"Total Cajas":1.23529411764706,"Status":"Entregado","Fecha de Pedido":"2026-06-12","Fecha de Entrega":"2026-06-18","Cliente":"VARIEDADES DE TODO PARA MICASA SOCIEDAD ANONIMA VARIEDADES DE TODO PARA MI CASA","Cod Cliente":"207","Peso Volumetrico":0.0457058823529412},{"OC":"OC-207-1503","Producto":"ROLL ON MUSK NARANJA 50ML","Code":"10-25","Total Unds":336.0,"Total Cajas":1.23529411764706,"Status":"Entregado","Fecha de Pedido":"2026-06-12","Fecha de Entrega":"2026-06-18","Cliente":"VARIEDADES DE TODO PARA MICASA SOCIEDAD ANONIMA VARIEDADES DE TODO PARA MI CASA","Cod Cliente":"207","Peso Volumetrico":0.0457058823529412},{"OC":"OC-207-1503","Producto":"ROLL ON TRIUNFO 50ML","Code":"10-35","Total Unds":336.0,"Total Cajas":1.23529411764706,"Status":"Entregado","Fecha de Pedido":"2026-06-12","Fecha de Entrega":"2026-06-18","Cliente":"VARIEDADES DE TODO PARA MICASA SOCIEDAD ANONIMA VARIEDADES DE TODO PARA MI CASA","Cod Cliente":"207","Peso Volumetrico":0.0457058823529412},{"OC":"OC-207-1503","Producto":"ROLL ON SWEET HONEY 50ML","Code":"10-29","Total Unds":240.0,"Total Cajas":0.882352941176471,"Status":"Entregado","Fecha de Pedido":"2026-06-12","Fecha de Entrega":"2026-06-18","Cliente":"VARIEDADES DE TODO PARA MICASA SOCIEDAD ANONIMA VARIEDADES DE TODO PARA MI CASA","Cod Cliente":"207","Peso Volumetrico":0.0326470588235294},{"OC":"OC-207-1503","Producto":"ROLL ON FARM AWAY 50ML","Code":"10-26","Total Unds":240.0,"Total Cajas":0.882352941176471,"Status":"Entregado","Fecha de Pedido":"2026-06-12","Fecha de Entrega":"2026-06-18","Cliente":"VARIEDADES DE TODO PARA MICASA SOCIEDAD ANONIMA VARIEDADES DE TODO PARA MI CASA","Cod Cliente":"207","Peso Volumetrico":0.0326470588235294},{"OC":"OC-207-1503","Producto":"ROLL ON CANDY 50ML","Code":"10-30","Total Unds":240.0,"Total Cajas":0.882352941176471,"Status":"Entregado","Fecha de Pedido":"2026-06-12","Fecha de Entrega":"2026-06-18","Cliente":"VARIEDADES DE TODO PARA MICASA SOCIEDAD ANONIMA VARIEDADES DE TODO PARA MI CASA","Cod Cliente":"207","Peso Volumetrico":0.0326470588235294},{"OC":"OC-207-1503","Producto":"ROLL ON IMARY 50ML","Code":"10-32","Total Unds":240.0,"Total Cajas":0.882352941176471,"Status":"Entregado","Fecha de Pedido":"2026-06-12","Fecha de Entrega":"2026-06-18","Cliente":"VARIEDADES DE TODO PARA MICASA SOCIEDAD ANONIMA VARIEDADES DE TODO PARA MI CASA","Cod Cliente":"207","Peso Volumetrico":0.0326470588235294},{"OC":"OC-207-1503","Producto":"ROLL ON INDIRA 50ML","Code":"10-28","Total Unds":240.0,"Total Cajas":0.882352941176471,"Status":"Entregado","Fecha de Pedido":"2026-06-12","Fecha de Entrega":"2026-06-18","Cliente":"VARIEDADES DE TODO PARA MICASA SOCIEDAD ANONIMA VARIEDADES DE TODO PARA MI CASA","Cod Cliente":"207","Peso Volumetrico":0.0326470588235294},{"OC":"OC-207-1503","Producto":"TRIPACK ROLL ON WILD COUNTY 75ML","Code":"10-52","Total Unds":132.0,"Total Cajas":5.28,"Status":"Entregado","Fecha de Pedido":"2026-06-12","Fecha de Entrega":"2026-06-18","Cliente":"VARIEDADES DE TODO PARA MICASA SOCIEDAD ANONIMA VARIEDADES DE TODO PARA MI CASA","Cod Cliente":"207","Peso Volumetrico":0.132},{"OC":"OC-207-1503","Producto":"TRIPACK ROLL ON SWEET HONEY 75ML","Code":"10-54","Total Unds":36.0,"Total Cajas":1.44,"Status":"Entregado","Fecha de Pedido":"2026-06-12","Fecha de Entrega":"2026-06-18","Cliente":"VARIEDADES DE TODO PARA MICASA SOCIEDAD ANONIMA VARIEDADES DE TODO PARA MI CASA","Cod Cliente":"207","Peso Volumetrico":0.036},{"OC":"OC-207-1503","Producto":"OFERTA CREMA INDIRA 237ML + ROLL ON INDIRA 75ML","Code":"30-20","Total Unds":36.0,"Total Cajas":0.144,"Status":"Entregado","Fecha de Pedido":"2026-06-12","Fecha de Entrega":"2026-06-18","Cliente":"VARIEDADES DE TODO PARA MICASA SOCIEDAD ANONIMA VARIEDADES DE TODO PARA MI CASA","Cod Cliente":"207","Peso Volumetrico":0.005328},{"OC":"OC-207-1503","Producto":"OFERTA CREMA IMARY 237ML + ROLL ON IMARY 75ML","Code":"30-21","Total Unds":36.0,"Total Cajas":0.144,"Status":"Entregado","Fecha de Pedido":"2026-06-12","Fecha de Entrega":"2026-06-18","Cliente":"VARIEDADES DE TODO PARA MICASA SOCIEDAD ANONIMA VARIEDADES DE TODO PARA MI CASA","Cod Cliente":"207","Peso Volumetrico":0.005328},{"OC":"OC-207-1503","Producto":"OFERTA CREMA CANDY 237ML + ROLL ON CANDY 75ML","Code":"30-22","Total Unds":36.0,"Total Cajas":0.144,"Status":"Entregado","Fecha de Pedido":"2026-06-12","Fecha de Entrega":"2026-06-18","Cliente":"VARIEDADES DE TODO PARA MICASA SOCIEDAD ANONIMA VARIEDADES DE TODO PARA MI CASA","Cod Cliente":"207","Peso Volumetrico":0.005328},{"OC":"OC-207-1503","Producto":"OFERTA CREMA FIEL 237ML + ROLL ON FIEL 75ML","Code":"30-23","Total Unds":36.0,"Total Cajas":0.144,"Status":"Entregado","Fecha de Pedido":"2026-06-12","Fecha de Entrega":"2026-06-18","Cliente":"VARIEDADES DE TODO PARA MICASA SOCIEDAD ANONIMA VARIEDADES DE TODO PARA MI CASA","Cod Cliente":"207","Peso Volumetrico":0.005328},{"OC":"OC-207-1503","Producto":"OFERTA TALCO SWEET HONEY 150GR + ROLL ON SWEET HONEY 75ML","Code":"10-57","Total Unds":36.0,"Total Cajas":0.144,"Status":"Entregado","Fecha de Pedido":"2026-06-12","Fecha de Entrega":"2026-06-18","Cliente":"VARIEDADES DE TODO PARA MICASA SOCIEDAD ANONIMA VARIEDADES DE TODO PARA MI CASA","Cod Cliente":"207","Peso Volumetrico":0.005328},{"OC":"OC-207-1503","Producto":"OFERTA TALCO FARM AWAY 150GR + ROLL ON FARM AWAY 75ML","Code":"10-58","Total Unds":36.0,"Total Cajas":0.144,"Status":"Entregado","Fecha de Pedido":"2026-06-12","Fecha de Entrega":"2026-06-18","Cliente":"VARIEDADES DE TODO PARA MICASA SOCIEDAD ANONIMA VARIEDADES DE TODO PARA MI CASA","Cod Cliente":"207","Peso Volumetrico":0.005328},{"OC":"OC-207-1503","Producto":"OFERTA TALCO WILL COUNTY 375GR + ROLL ON WILL COUNTY 75ML","Code":"10-53","Total Unds":30.0,"Total Cajas":0.12,"Status":"Entregado","Fecha de Pedido":"2026-06-12","Fecha de Entrega":"2026-06-18","Cliente":"VARIEDADES DE TODO PARA MICASA SOCIEDAD ANONIMA VARIEDADES DE TODO PARA MI CASA","Cod Cliente":"207","Peso Volumetrico":0.00444},{"OC":"OC-207-1503","Producto":"OFERTA TALCO FARM AWAY 375GR + ROLL ON FARM AWAY 75ML","Code":"10-55","Total Unds":30.0,"Total Cajas":0.12,"Status":"Entregado","Fecha de Pedido":"2026-06-12","Fecha de Entrega":"2026-06-18","Cliente":"VARIEDADES DE TODO PARA MICASA SOCIEDAD ANONIMA VARIEDADES DE TODO PARA MI CASA","Cod Cliente":"207","Peso Volumetrico":0.00444},{"OC":"OC-207-1503","Producto":"OFERTA TALCO CHIEF 375GR  + ROLL ON BLACK SOFT 75ML","Code":"10-56","Total Unds":30.0,"Total Cajas":0.12,"Status":"Entregado","Fecha de Pedido":"2026-06-12","Fecha de Entrega":"2026-06-18","Cliente":"VARIEDADES DE TODO PARA MICASA SOCIEDAD ANONIMA VARIEDADES DE TODO PARA MI CASA","Cod Cliente":"207","Peso Volumetrico":0.00444},{"OC":"OC-207-1503","Producto":"OFERTA TALCO SWEET HONEY 375GR + ROLL ON SWEET HONEY 75ML","Code":"10-59","Total Unds":30.0,"Total Cajas":0.12,"Status":"Entregado","Fecha de Pedido":"2026-06-12","Fecha de Entrega":"2026-06-18","Cliente":"VARIEDADES DE TODO PARA MICASA SOCIEDAD ANONIMA VARIEDADES DE TODO PARA MI CASA","Cod Cliente":"207","Peso Volumetrico":0.00444},{"OC":"OC-207-1503","Producto":"GEL PLASTIMAX 250GR","Code":"20-00","Total Unds":240.0,"Total Cajas":4.0,"Status":"Entregado","Fecha de Pedido":"2026-06-12","Fecha de Entrega":"2026-06-18","Cliente":"VARIEDADES DE TODO PARA MICASA SOCIEDAD ANONIMA VARIEDADES DE TODO PARA MI CASA","Cod Cliente":"207","Peso Volumetrico":0.096},{"OC":"OC-207-1503","Producto":"GEL PLASTIMAX 950GR","Code":"20-01","Total Unds":144.0,"Total Cajas":4.8,"Status":"Entregado","Fecha de Pedido":"2026-06-12","Fecha de Entrega":"2026-06-18","Cliente":"VARIEDADES DE TODO PARA MICASA SOCIEDAD ANONIMA VARIEDADES DE TODO PARA MI CASA","Cod Cliente":"207","Peso Volumetrico":0.1776},{"OC":"OC-207-1503","Producto":"SHAMP FRACHEL AGUACATE 500ML","Code":"60-02","Total Unds":24.0,"Total Cajas":0.96,"Status":"Entregado","Fecha de Pedido":"2026-06-12","Fecha de Entrega":"2026-06-18","Cliente":"VARIEDADES DE TODO PARA MICASA SOCIEDAD ANONIMA VARIEDADES DE TODO PARA MI CASA","Cod Cliente":"207","Peso Volumetrico":0.024},{"OC":"OC-207-1503","Producto":"SHAMP FRACHEL MANZANILLA 500ML","Code":"60-04","Total Unds":24.0,"Total Cajas":0.96,"Status":"Entregado","Fecha de Pedido":"2026-06-12","Fecha de Entrega":"2026-06-18","Cliente":"VARIEDADES DE TODO PARA MICASA SOCIEDAD ANONIMA VARIEDADES DE TODO PARA MI CASA","Cod Cliente":"207","Peso Volumetrico":0.024},{"OC":"OC-207-1503","Producto":"SHAMP FRACHEL MIEL 500ML","Code":"60-05","Total Unds":24.0,"Total Cajas":0.96,"Status":"Entregado","Fecha de Pedido":"2026-06-12","Fecha de Entrega":"2026-06-18","Cliente":"VARIEDADES DE TODO PARA MICASA SOCIEDAD ANONIMA VARIEDADES DE TODO PARA MI CASA","Cod Cliente":"207","Peso Volumetrico":0.024},{"OC":"OC-207-1503","Producto":"SHAMP FRACHEL FRESA 500ML","Code":"60-06","Total Unds":24.0,"Total Cajas":0.96,"Status":"Entregado","Fecha de Pedido":"2026-06-12","Fecha de Entrega":"2026-06-18","Cliente":"VARIEDADES DE TODO PARA MICASA SOCIEDAD ANONIMA VARIEDADES DE TODO PARA MI CASA","Cod Cliente":"207","Peso Volumetrico":0.024},{"OC":"OC-207-1503","Producto":"SHAMP FRACHEL SABILA 500ML","Code":"60-08","Total Unds":24.0,"Total Cajas":0.96,"Status":"Entregado","Fecha de Pedido":"2026-06-12","Fecha de Entrega":"2026-06-18","Cliente":"VARIEDADES DE TODO PARA MICASA SOCIEDAD ANONIMA VARIEDADES DE TODO PARA MI CASA","Cod Cliente":"207","Peso Volumetrico":0.024},{"OC":"OC-207-1503","Producto":"SHAMP FRACHEL MANZANA 500ML","Code":"60-09","Total Unds":24.0,"Total Cajas":0.96,"Status":"Entregado","Fecha de Pedido":"2026-06-12","Fecha de Entrega":"2026-06-18","Cliente":"VARIEDADES DE TODO PARA MICASA SOCIEDAD ANONIMA VARIEDADES DE TODO PARA MI CASA","Cod Cliente":"207","Peso Volumetrico":0.024},{"OC":"OC-207-1503","Producto":"SHAMP FRACHEL PEPINO 500ML","Code":"60-10","Total Unds":24.0,"Total Cajas":0.96,"Status":"Entregado","Fecha de Pedido":"2026-06-12","Fecha de Entrega":"2026-06-18","Cliente":"VARIEDADES DE TODO PARA MICASA SOCIEDAD ANONIMA VARIEDADES DE TODO PARA MI CASA","Cod Cliente":"207","Peso Volumetrico":0.024},{"OC":"OC-207-1503","Producto":"CREMA ALGAMARINA VIT A 437ML","Code":"30-00","Total Unds":60.0,"Total Cajas":1.11111111111111,"Status":"Entregado","Fecha de Pedido":"2026-06-12","Fecha de Entrega":"2026-06-18","Cliente":"VARIEDADES DE TODO PARA MICASA SOCIEDAD ANONIMA VARIEDADES DE TODO PARA MI CASA","Cod Cliente":"207","Peso Volumetrico":0.0411111111111111},{"OC":"OC-207-1503","Producto":"CREMA ALGAMARINA VIT E 437ML","Code":"30-01","Total Unds":60.0,"Total Cajas":1.11111111111111,"Status":"Entregado","Fecha de Pedido":"2026-06-12","Fecha de Entrega":"2026-06-18","Cliente":"VARIEDADES DE TODO PARA MICASA SOCIEDAD ANONIMA VARIEDADES DE TODO PARA MI CASA","Cod Cliente":"207","Peso Volumetrico":0.0411111111111111},{"OC":"OC-207-1503","Producto":"CREMA ALGAMARINA ALOE 437ML","Code":"30-02","Total Unds":48.0,"Total Cajas":0.888888888888889,"Status":"Entregado","Fecha de Pedido":"2026-06-12","Fecha de Entrega":"2026-06-18","Cliente":"VARIEDADES DE TODO PARA MICASA SOCIEDAD ANONIMA VARIEDADES DE TODO PARA MI CASA","Cod Cliente":"207","Peso Volumetrico":0.0328888888888889},{"OC":"OC-207-1503","Producto":"CREMA SWEET HONEY 237ML","Code":"30-09","Total Unds":60.0,"Total Cajas":1.42857142857143,"Status":"Entregado","Fecha de Pedido":"2026-06-12","Fecha de Entrega":"2026-06-18","Cliente":"VARIEDADES DE TODO PARA MICASA SOCIEDAD ANONIMA VARIEDADES DE TODO PARA MI CASA","Cod Cliente":"207","Peso Volumetrico":0.0342857142857143},{"OC":"OC-207-1503","Producto":"CREMA IMARY 237ML","Code":"30-10","Total Unds":60.0,"Total Cajas":1.42857142857143,"Status":"Entregado","Fecha de Pedido":"2026-06-12","Fecha de Entrega":"2026-06-18","Cliente":"VARIEDADES DE TODO PARA MICASA SOCIEDAD ANONIMA VARIEDADES DE TODO PARA MI CASA","Cod Cliente":"207","Peso Volumetrico":0.0342857142857143},{"OC":"OC-207-1503","Producto":"CREMA FARM AWAY 237ML","Code":"30-11","Total Unds":60.0,"Total Cajas":1.42857142857143,"Status":"Entregado","Fecha de Pedido":"2026-06-12","Fecha de Entrega":"2026-06-18","Cliente":"VARIEDADES DE TODO PARA MICASA SOCIEDAD ANONIMA VARIEDADES DE TODO PARA MI CASA","Cod Cliente":"207","Peso Volumetrico":0.0342857142857143},{"OC":"OC-207-1503","Producto":"CREMA CANDY 237ML","Code":"30-12","Total Unds":60.0,"Total Cajas":1.42857142857143,"Status":"Entregado","Fecha de Pedido":"2026-06-12","Fecha de Entrega":"2026-06-18","Cliente":"VARIEDADES DE TODO PARA MICASA SOCIEDAD ANONIMA VARIEDADES DE TODO PARA MI CASA","Cod Cliente":"207","Peso Volumetrico":0.0342857142857143},{"OC":"OC-207-1503","Producto":"CREMA INDIRA 237ML","Code":"30-13","Total Unds":60.0,"Total Cajas":1.42857142857143,"Status":"Entregado","Fecha de Pedido":"2026-06-12","Fecha de Entrega":"2026-06-18","Cliente":"VARIEDADES DE TODO PARA MICASA SOCIEDAD ANONIMA VARIEDADES DE TODO PARA MI CASA","Cod Cliente":"207","Peso Volumetrico":0.0342857142857143},{"OC":"OC-207-1503","Producto":"CREMA FIEL 237ML","Code":"30-14","Total Unds":60.0,"Total Cajas":1.42857142857143,"Status":"Entregado","Fecha de Pedido":"2026-06-12","Fecha de Entrega":"2026-06-18","Cliente":"VARIEDADES DE TODO PARA MICASA SOCIEDAD ANONIMA VARIEDADES DE TODO PARA MI CASA","Cod Cliente":"207","Peso Volumetrico":0.0342857142857143},{"OC":"OC-207-1503","Producto":"PERFUME SWEET HONEY 50ML","Code":"40-00","Total Unds":24.0,"Total Cajas":1.0,"Status":"Entregado","Fecha de Pedido":"2026-06-12","Fecha de Entrega":"2026-06-18","Cliente":"VARIEDADES DE TODO PARA MICASA SOCIEDAD ANONIMA VARIEDADES DE TODO PARA MI CASA","Cod Cliente":"207","Peso Volumetrico":0.024},{"OC":"OC-207-1503","Producto":"PERFUME FIEL 100ML","Code":"40-02","Total Unds":24.0,"Total Cajas":1.0,"Status":"Entregado","Fecha de Pedido":"2026-06-12","Fecha de Entrega":"2026-06-18","Cliente":"VARIEDADES DE TODO PARA MICASA SOCIEDAD ANONIMA VARIEDADES DE TODO PARA MI CASA","Cod Cliente":"207","Peso Volumetrico":0.024},{"OC":"OC-207-1503","Producto":"PERFUME INDIRA 100ML","Code":"40-03","Total Unds":24.0,"Total Cajas":1.0,"Status":"Entregado","Fecha de Pedido":"2026-06-12","Fecha de Entrega":"2026-06-18","Cliente":"VARIEDADES DE TODO PARA MICASA SOCIEDAD ANONIMA VARIEDADES DE TODO PARA MI CASA","Cod Cliente":"207","Peso Volumetrico":0.024},{"OC":"OC-207-1503","Producto":"COLONIA EMANUEL 250ML","Code":"40-04","Total Unds":24.0,"Total Cajas":0.6,"Status":"Entregado","Fecha de Pedido":"2026-06-12","Fecha de Entrega":"2026-06-18","Cliente":"VARIEDADES DE TODO PARA MICASA SOCIEDAD ANONIMA VARIEDADES DE TODO PARA MI CASA","Cod Cliente":"207","Peso Volumetrico":0.0144},{"OC":"OC-207-1503","Producto":"PERFUME ROSE MEN 100ML","Code":"40-08","Total Unds":24.0,"Total Cajas":1.0,"Status":"Entregado","Fecha de Pedido":"2026-06-12","Fecha de Entrega":"2026-06-18","Cliente":"VARIEDADES DE TODO PARA MICASA SOCIEDAD ANONIMA VARIEDADES DE TODO PARA MI CASA","Cod Cliente":"207","Peso Volumetrico":0.024},{"OC":"OC-207-1503","Producto":"TALCO BABY GRD 575GR","Code":"50-01","Total Unds":24.0,"Total Cajas":0.75,"Status":"Entregado","Fecha de Pedido":"2026-06-12","Fecha de Entrega":"2026-06-18","Cliente":"VARIEDADES DE TODO PARA MICASA SOCIEDAD ANONIMA VARIEDADES DE TODO PARA MI CASA","Cod Cliente":"207","Peso Volumetrico":0.036},{"OC":"OC-207-1503","Producto":"TALCO CHIEF 375GR","Code":"50-02","Total Unds":120.0,"Total Cajas":3.0,"Status":"Entregado","Fecha de Pedido":"2026-06-12","Fecha de Entrega":"2026-06-18","Cliente":"VARIEDADES DE TODO PARA MICASA SOCIEDAD ANONIMA VARIEDADES DE TODO PARA MI CASA","Cod Cliente":"207","Peso Volumetrico":0.111},{"OC":"OC-207-1503","Producto":"TALCO SWEET HONEY 375GR","Code":"50-04","Total Unds":24.0,"Total Cajas":0.6,"Status":"Entregado","Fecha de Pedido":"2026-06-12","Fecha de Entrega":"2026-06-18","Cliente":"VARIEDADES DE TODO PARA MICASA SOCIEDAD ANONIMA VARIEDADES DE TODO PARA MI CASA","Cod Cliente":"207","Peso Volumetrico":0.0222},{"OC":"OC-207-1503","Producto":"TALCO WILL COUNTY 375GR","Code":"50-05","Total Unds":120.0,"Total Cajas":3.0,"Status":"Entregado","Fecha de Pedido":"2026-06-12","Fecha de Entrega":"2026-06-18","Cliente":"VARIEDADES DE TODO PARA MICASA SOCIEDAD ANONIMA VARIEDADES DE TODO PARA MI CASA","Cod Cliente":"207","Peso Volumetrico":0.111},{"OC":"OC-207-1503","Producto":"TALCO FARM AWAY 375GR","Code":"50-06","Total Unds":24.0,"Total Cajas":0.6,"Status":"Entregado","Fecha de Pedido":"2026-06-12","Fecha de Entrega":"2026-06-18","Cliente":"VARIEDADES DE TODO PARA MICASA SOCIEDAD ANONIMA VARIEDADES DE TODO PARA MI CASA","Cod Cliente":"207","Peso Volumetrico":0.0222},{"OC":"OC-207-1503","Producto":"TALCO ROSAS 350GR","Code":"50-09","Total Unds":24.0,"Total Cajas":0.444444444444444,"Status":"Entregado","Fecha de Pedido":"2026-06-12","Fecha de Entrega":"2026-06-18","Cliente":"VARIEDADES DE TODO PARA MICASA SOCIEDAD ANONIMA VARIEDADES DE TODO PARA MI CASA","Cod Cliente":"207","Peso Volumetrico":0.0164444444444444},{"OC":"OC-207-1503","Producto":"TALCO BABY PEQ 150GR","Code":"50-07","Total Unds":36.0,"Total Cajas":0.36,"Status":"Entregado","Fecha de Pedido":"2026-06-12","Fecha de Entrega":"2026-06-18","Cliente":"VARIEDADES DE TODO PARA MICASA SOCIEDAD ANONIMA VARIEDADES DE TODO PARA MI CASA","Cod Cliente":"207","Peso Volumetrico":0.01332},{"OC":"OC-207-1503","Producto":"TALCO WILL COUNTY 150GR","Code":"50-10","Total Unds":120.0,"Total Cajas":1.2,"Status":"Entregado","Fecha de Pedido":"2026-06-12","Fecha de Entrega":"2026-06-18","Cliente":"VARIEDADES DE TODO PARA MICASA SOCIEDAD ANONIMA VARIEDADES DE TODO PARA MI CASA","Cod Cliente":"207","Peso Volumetrico":0.0444},{"OC":"OC-207-1503","Producto":"TALCO SWEET HONEY 150GR","Code":"50-11","Total Unds":24.0,"Total Cajas":0.24,"Status":"Entregado","Fecha de Pedido":"2026-06-12","Fecha de Entrega":"2026-06-18","Cliente":"VARIEDADES DE TODO PARA MICASA SOCIEDAD ANONIMA VARIEDADES DE TODO PARA MI CASA","Cod Cliente":"207","Peso Volumetrico":0.00888},{"OC":"OC-207-1503","Producto":"TALCO FARM AWAY 150GR","Code":"50-12","Total Unds":24.0,"Total Cajas":0.24,"Status":"Entregado","Fecha de Pedido":"2026-06-12","Fecha de Entrega":"2026-06-18","Cliente":"VARIEDADES DE TODO PARA MICASA SOCIEDAD ANONIMA VARIEDADES DE TODO PARA MI CASA","Cod Cliente":"207","Peso Volumetrico":0.00888},{"OC":"OC-207-1503","Producto":"TALCO CHIEF 150GR","Code":"50-13","Total Unds":120.0,"Total Cajas":1.2,"Status":"Entregado","Fecha de Pedido":"2026-06-12","Fecha de Entrega":"2026-06-18","Cliente":"VARIEDADES DE TODO PARA MICASA SOCIEDAD ANONIMA VARIEDADES DE TODO PARA MI CASA","Cod Cliente":"207","Peso Volumetrico":0.0444},{"OC":"OC-207-1503","Producto":"TALCO ROSE MEN 150GR","Code":"50-14","Total Unds":120.0,"Total Cajas":1.2,"Status":"Entregado","Fecha de Pedido":"2026-06-12","Fecha de Entrega":"2026-06-18","Cliente":"VARIEDADES DE TODO PARA MICASA SOCIEDAD ANONIMA VARIEDADES DE TODO PARA MI CASA","Cod Cliente":"207","Peso Volumetrico":0.0444},{"OC":"OC-207-1503","Producto":"SHAMP BABY GRD 946ML","Code":"60-00","Total Unds":24.0,"Total Cajas":1.5,"Status":"Entregado","Fecha de Pedido":"2026-06-12","Fecha de Entrega":"2026-06-18","Cliente":"VARIEDADES DE TODO PARA MICASA SOCIEDAD ANONIMA VARIEDADES DE TODO PARA MI CASA","Cod Cliente":"207","Peso Volumetrico":0.0375},{"OC":"OC-207-1503","Producto":"SHAMP BABY PEQ 310ML","Code":"60-01","Total Unds":36.0,"Total Cajas":1.0,"Status":"Entregado","Fecha de Pedido":"2026-06-12","Fecha de Entrega":"2026-06-18","Cliente":"VARIEDADES DE TODO PARA MICASA SOCIEDAD ANONIMA VARIEDADES DE TODO PARA MI CASA","Cod Cliente":"207","Peso Volumetrico":0.024},{"OC":"OC-011-1513","Producto":"ROLL ON WILL COUNTY 75ML","Code":"10-01","Total Unds":96.0,"Total Cajas":0.5,"Status":"Alistado","Fecha de Pedido":"2026-06-16","Fecha de Entrega":"2026-06-22","Cliente":"ALMACENES EL REY LIMITADA ","Cod Cliente":"011","Peso Volumetrico":0.0185},{"OC":"OC-011-1513","Producto":"TALCO ROSAS 350GR","Code":"50-09","Total Unds":72.0,"Total Cajas":1.33333333333333,"Status":"Alistado","Fecha de Pedido":"2026-06-16","Fecha de Entrega":"2026-06-22","Cliente":"ALMACENES EL REY LIMITADA ","Cod Cliente":"011","Peso Volumetrico":0.0493333333333333},{"OC":"OC-011-1514","Producto":"CREMA ALGAMARINA ALOE 437ML","Code":"30-02","Total Unds":48.0,"Total Cajas":0.888888888888889,"Status":"Alistado","Fecha de Pedido":"2026-06-16","Fecha de Entrega":"2026-06-22","Cliente":"ALMACENES EL REY LIMITADA ","Cod Cliente":"011","Peso Volumetrico":0.0328888888888889},{"OC":"OC-011-1514","Producto":"ROLL ON WILL COUNTY 75ML","Code":"10-01","Total Unds":192.0,"Total Cajas":1.0,"Status":"Alistado","Fecha de Pedido":"2026-06-16","Fecha de Entrega":"2026-06-22","Cliente":"ALMACENES EL REY LIMITADA ","Cod Cliente":"011","Peso Volumetrico":0.037},{"OC":"OC-011-1514","Producto":"ROLL ON SWEET HONEY 75ML","Code":"10-02","Total Unds":96.0,"Total Cajas":0.5,"Status":"Alistado","Fecha de Pedido":"2026-06-16","Fecha de Entrega":"2026-06-22","Cliente":"ALMACENES EL REY LIMITADA ","Cod Cliente":"011","Peso Volumetrico":0.0185},{"OC":"OC-011-1514","Producto":"TALCO ROSAS 350GR","Code":"50-09","Total Unds":48.0,"Total Cajas":0.888888888888889,"Status":"Alistado","Fecha de Pedido":"2026-06-16","Fecha de Entrega":"2026-06-22","Cliente":"ALMACENES EL REY LIMITADA ","Cod Cliente":"011","Peso Volumetrico":0.0328888888888889},{"OC":"OC-011-1515","Producto":"CREMA ALGAMARINA ALOE 437ML","Code":"30-02","Total Unds":72.0,"Total Cajas":1.33333333333333,"Status":"Alistado","Fecha de Pedido":"2026-06-16","Fecha de Entrega":"2026-06-22","Cliente":"ALMACENES EL REY LIMITADA ","Cod Cliente":"011","Peso Volumetrico":0.0493333333333333},{"OC":"OC-011-1515","Producto":"ROLL ON WILL COUNTY 75ML","Code":"10-01","Total Unds":192.0,"Total Cajas":1.0,"Status":"Alistado","Fecha de Pedido":"2026-06-16","Fecha de Entrega":"2026-06-22","Cliente":"ALMACENES EL REY LIMITADA ","Cod Cliente":"011","Peso Volumetrico":0.037},{"OC":"OC-011-1515","Producto":"GEL PLASTIMAX 950GR","Code":"20-01","Total Unds":48.0,"Total Cajas":1.6,"Status":"Alistado","Fecha de Pedido":"2026-06-16","Fecha de Entrega":"2026-06-22","Cliente":"ALMACENES EL REY LIMITADA ","Cod Cliente":"011","Peso Volumetrico":0.0592},{"OC":"OC-011-1515","Producto":"TALCO WILL COUNTY 375GR","Code":"50-05","Total Unds":30.0,"Total Cajas":0.75,"Status":"Alistado","Fecha de Pedido":"2026-06-16","Fecha de Entrega":"2026-06-22","Cliente":"ALMACENES EL REY LIMITADA ","Cod Cliente":"011","Peso Volumetrico":0.02775},{"OC":"OC-011-1516","Producto":"CREMA ALGAMARINA ALOE 437ML","Code":"30-02","Total Unds":24.0,"Total Cajas":0.444444444444444,"Status":"Alistado","Fecha de Pedido":"2026-06-16","Fecha de Entrega":"2026-06-22","Cliente":"ALMACENES EL REY LIMITADA ","Cod Cliente":"011","Peso Volumetrico":0.0164444444444444},{"OC":"OC-011-1516","Producto":"ROLL ON BLACK SOFT 75ML","Code":"10-03","Total Unds":96.0,"Total Cajas":0.5,"Status":"Alistado","Fecha de Pedido":"2026-06-16","Fecha de Entrega":"2026-06-22","Cliente":"ALMACENES EL REY LIMITADA ","Cod Cliente":"011","Peso Volumetrico":0.0185},{"OC":"OC-011-1516","Producto":"TALCO ROSAS 350GR","Code":"50-09","Total Unds":72.0,"Total Cajas":1.33333333333333,"Status":"Alistado","Fecha de Pedido":"2026-06-16","Fecha de Entrega":"2026-06-22","Cliente":"ALMACENES EL REY LIMITADA ","Cod Cliente":"011","Peso Volumetrico":0.0493333333333333},{"OC":"OC-011-1516","Producto":"TALCO WILL COUNTY 375GR","Code":"50-05","Total Unds":60.0,"Total Cajas":1.5,"Status":"Alistado","Fecha de Pedido":"2026-06-16","Fecha de Entrega":"2026-06-22","Cliente":"ALMACENES EL REY LIMITADA ","Cod Cliente":"011","Peso Volumetrico":0.0555},{"OC":"OC-011-1517","Producto":"CREMA ALGAMARINA ALOE 437ML","Code":"30-02","Total Unds":48.0,"Total Cajas":0.888888888888889,"Status":"Alistado","Fecha de Pedido":"2026-06-16","Fecha de Entrega":"2026-06-22","Cliente":"ALMACENES EL REY LIMITADA ","Cod Cliente":"011","Peso Volumetrico":0.0328888888888889},{"OC":"OC-011-1517","Producto":"ROLL ON WILL COUNTY 75ML","Code":"10-01","Total Unds":192.0,"Total Cajas":1.0,"Status":"Alistado","Fecha de Pedido":"2026-06-16","Fecha de Entrega":"2026-06-22","Cliente":"ALMACENES EL REY LIMITADA ","Cod Cliente":"011","Peso Volumetrico":0.037},{"OC":"OC-011-1517","Producto":"TALCO ROSAS 350GR","Code":"50-09","Total Unds":72.0,"Total Cajas":1.33333333333333,"Status":"Alistado","Fecha de Pedido":"2026-06-16","Fecha de Entrega":"2026-06-22","Cliente":"ALMACENES EL REY LIMITADA ","Cod Cliente":"011","Peso Volumetrico":0.0493333333333333},{"OC":"OC-011-1517","Producto":"TALCO WILL COUNTY 375GR","Code":"50-05","Total Unds":30.0,"Total Cajas":0.75,"Status":"Alistado","Fecha de Pedido":"2026-06-16","Fecha de Entrega":"2026-06-22","Cliente":"ALMACENES EL REY LIMITADA ","Cod Cliente":"011","Peso Volumetrico":0.02775},{"OC":"OC-011-1518","Producto":"ROLL ON WILL COUNTY 75ML","Code":"10-01","Total Unds":96.0,"Total Cajas":0.5,"Status":"Alistado","Fecha de Pedido":"2026-06-16","Fecha de Entrega":"2026-06-22","Cliente":"ALMACENES EL REY LIMITADA ","Cod Cliente":"011","Peso Volumetrico":0.0185},{"OC":"OC-011-1518","Producto":"TALCO ROSAS 350GR","Code":"50-09","Total Unds":24.0,"Total Cajas":0.444444444444444,"Status":"Alistado","Fecha de Pedido":"2026-06-16","Fecha de Entrega":"2026-06-22","Cliente":"ALMACENES EL REY LIMITADA ","Cod Cliente":"011","Peso Volumetrico":0.0164444444444444},{"OC":"OC-011-1518","Producto":"TALCO WILL COUNTY 375GR","Code":"50-05","Total Unds":60.0,"Total Cajas":1.5,"Status":"Alistado","Fecha de Pedido":"2026-06-16","Fecha de Entrega":"2026-06-22","Cliente":"ALMACENES EL REY LIMITADA ","Cod Cliente":"011","Peso Volumetrico":0.0555},{"OC":"OC-011-1519","Producto":"ROLL ON WILL COUNTY 75ML","Code":"10-01","Total Unds":288.0,"Total Cajas":1.5,"Status":"Alistado","Fecha de Pedido":"2026-06-16","Fecha de Entrega":"2026-06-22","Cliente":"ALMACENES EL REY LIMITADA ","Cod Cliente":"011","Peso Volumetrico":0.0555},{"OC":"OC-011-1519","Producto":"ROLL ON SWEET HONEY 75ML","Code":"10-02","Total Unds":96.0,"Total Cajas":0.5,"Status":"Alistado","Fecha de Pedido":"2026-06-16","Fecha de Entrega":"2026-06-22","Cliente":"ALMACENES EL REY LIMITADA ","Cod Cliente":"011","Peso Volumetrico":0.0185},{"OC":"OC-011-1519","Producto":"TALCO ROSAS 350GR","Code":"50-09","Total Unds":120.0,"Total Cajas":2.22222222222222,"Status":"Alistado","Fecha de Pedido":"2026-06-16","Fecha de Entrega":"2026-06-22","Cliente":"ALMACENES EL REY LIMITADA ","Cod Cliente":"011","Peso Volumetrico":0.0822222222222222},{"OC":"OC-011-1519","Producto":"TALCO WILL COUNTY 375GR","Code":"50-05","Total Unds":30.0,"Total Cajas":0.75,"Status":"Alistado","Fecha de Pedido":"2026-06-16","Fecha de Entrega":"2026-06-22","Cliente":"ALMACENES EL REY LIMITADA ","Cod Cliente":"011","Peso Volumetrico":0.02775},{"OC":"OC-011-1520","Producto":"CREMA ALGAMARINA ALOE 437ML","Code":"30-02","Total Unds":48.0,"Total Cajas":0.888888888888889,"Status":"Alistado","Fecha de Pedido":"2026-06-16","Fecha de Entrega":"2026-06-22","Cliente":"ALMACENES EL REY LIMITADA ","Cod Cliente":"011","Peso Volumetrico":0.0328888888888889},{"OC":"OC-011-1520","Producto":"GEL PLASTIMAX 950GR","Code":"20-01","Total Unds":48.0,"Total Cajas":1.6,"Status":"Alistado","Fecha de Pedido":"2026-06-16","Fecha de Entrega":"2026-06-22","Cliente":"ALMACENES EL REY LIMITADA ","Cod Cliente":"011","Peso Volumetrico":0.0592},{"OC":"OC-011-1520","Producto":"TALCO WILL COUNTY 375GR","Code":"50-05","Total Unds":30.0,"Total Cajas":0.75,"Status":"Alistado","Fecha de Pedido":"2026-06-16","Fecha de Entrega":"2026-06-22","Cliente":"ALMACENES EL REY LIMITADA ","Cod Cliente":"011","Peso Volumetrico":0.02775},{"OC":"OC-011-1521","Producto":"CREMA ALGAMARINA ALOE 437ML","Code":"30-02","Total Unds":72.0,"Total Cajas":1.33333333333333,"Status":"Alistado","Fecha de Pedido":"2026-06-16","Fecha de Entrega":"2026-06-22","Cliente":"ALMACENES EL REY LIMITADA ","Cod Cliente":"011","Peso Volumetrico":0.0493333333333333},{"OC":"OC-011-1521","Producto":"CREMA INDIRA 237ML","Code":"30-13","Total Unds":36.0,"Total Cajas":0.857142857142857,"Status":"Alistado","Fecha de Pedido":"2026-06-16","Fecha de Entrega":"2026-06-22","Cliente":"ALMACENES EL REY LIMITADA ","Cod Cliente":"011","Peso Volumetrico":0.0205714285714286},{"OC":"OC-011-1521","Producto":"ROLL ON WILL COUNTY 75ML","Code":"10-01","Total Unds":96.0,"Total Cajas":0.5,"Status":"Alistado","Fecha de Pedido":"2026-06-16","Fecha de Entrega":"2026-06-22","Cliente":"ALMACENES EL REY LIMITADA ","Cod Cliente":"011","Peso Volumetrico":0.0185},{"OC":"OC-011-1521","Producto":"ROLL ON SWEET HONEY 75ML","Code":"10-02","Total Unds":96.0,"Total Cajas":0.5,"Status":"Alistado","Fecha de Pedido":"2026-06-16","Fecha de Entrega":"2026-06-22","Cliente":"ALMACENES EL REY LIMITADA ","Cod Cliente":"011","Peso Volumetrico":0.0185},{"OC":"OC-011-1521","Producto":"GEL PLASTIMAX 950GR","Code":"20-01","Total Unds":48.0,"Total Cajas":1.6,"Status":"Alistado","Fecha de Pedido":"2026-06-16","Fecha de Entrega":"2026-06-22","Cliente":"ALMACENES EL REY LIMITADA ","Cod Cliente":"011","Peso Volumetrico":0.0592},{"OC":"OC-011-1521","Producto":"TALCO ROSAS 350GR","Code":"50-09","Total Unds":48.0,"Total Cajas":0.888888888888889,"Status":"Alistado","Fecha de Pedido":"2026-06-16","Fecha de Entrega":"2026-06-22","Cliente":"ALMACENES EL REY LIMITADA ","Cod Cliente":"011","Peso Volumetrico":0.0328888888888889},{"OC":"OC-011-1521","Producto":"TALCO WILL COUNTY 375GR","Code":"50-05","Total Unds":60.0,"Total Cajas":1.5,"Status":"Alistado","Fecha de Pedido":"2026-06-16","Fecha de Entrega":"2026-06-22","Cliente":"ALMACENES EL REY LIMITADA ","Cod Cliente":"011","Peso Volumetrico":0.0555},{"OC":"OC-011-1522","Producto":"CREMA ALGAMARINA ALOE 437ML","Code":"30-02","Total Unds":48.0,"Total Cajas":0.888888888888889,"Status":"Alistado","Fecha de Pedido":"2026-06-16","Fecha de Entrega":"2026-06-22","Cliente":"ALMACENES EL REY LIMITADA ","Cod Cliente":"011","Peso Volumetrico":0.0328888888888889},{"OC":"OC-011-1522","Producto":"ROLL ON SWEET HONEY 75ML","Code":"10-02","Total Unds":96.0,"Total Cajas":0.5,"Status":"Alistado","Fecha de Pedido":"2026-06-16","Fecha de Entrega":"2026-06-22","Cliente":"ALMACENES EL REY LIMITADA ","Cod Cliente":"011","Peso Volumetrico":0.0185},{"OC":"OC-011-1522","Producto":"TALCO ROSAS 350GR","Code":"50-09","Total Unds":72.0,"Total Cajas":1.33333333333333,"Status":"Alistado","Fecha de Pedido":"2026-06-16","Fecha de Entrega":"2026-06-22","Cliente":"ALMACENES EL REY LIMITADA ","Cod Cliente":"011","Peso Volumetrico":0.0493333333333333},{"OC":"OC-011-1522","Producto":"TALCO WILL COUNTY 375GR","Code":"50-05","Total Unds":60.0,"Total Cajas":1.5,"Status":"Alistado","Fecha de Pedido":"2026-06-16","Fecha de Entrega":"2026-06-22","Cliente":"ALMACENES EL REY LIMITADA ","Cod Cliente":"011","Peso Volumetrico":0.0555},{"OC":"OC-011-1523","Producto":"CREMA INDIRA 237ML","Code":"30-13","Total Unds":36.0,"Total Cajas":0.857142857142857,"Status":"Alistado","Fecha de Pedido":"2026-06-16","Fecha de Entrega":"2026-06-22","Cliente":"ALMACENES EL REY LIMITADA ","Cod Cliente":"011","Peso Volumetrico":0.0205714285714286},{"OC":"OC-011-1523","Producto":"ROLL ON WILL COUNTY 75ML","Code":"10-01","Total Unds":96.0,"Total Cajas":0.5,"Status":"Alistado","Fecha de Pedido":"2026-06-16","Fecha de Entrega":"2026-06-22","Cliente":"ALMACENES EL REY LIMITADA ","Cod Cliente":"011","Peso Volumetrico":0.0185},{"OC":"OC-011-1523","Producto":"ROLL ON SWEET HONEY 75ML","Code":"10-02","Total Unds":96.0,"Total Cajas":0.5,"Status":"Alistado","Fecha de Pedido":"2026-06-16","Fecha de Entrega":"2026-06-22","Cliente":"ALMACENES EL REY LIMITADA ","Cod Cliente":"011","Peso Volumetrico":0.0185},{"OC":"OC-011-1523","Producto":"TALCO ROSAS 350GR","Code":"50-09","Total Unds":72.0,"Total Cajas":1.33333333333333,"Status":"Alistado","Fecha de Pedido":"2026-06-16","Fecha de Entrega":"2026-06-22","Cliente":"ALMACENES EL REY LIMITADA ","Cod Cliente":"011","Peso Volumetrico":0.0493333333333333},{"OC":"OC-011-1523","Producto":"TALCO WILL COUNTY 375GR","Code":"50-05","Total Unds":60.0,"Total Cajas":1.5,"Status":"Alistado","Fecha de Pedido":"2026-06-16","Fecha de Entrega":"2026-06-22","Cliente":"ALMACENES EL REY LIMITADA ","Cod Cliente":"011","Peso Volumetrico":0.0555},{"OC":"OC-011-1524","Producto":"CREMA SWEET HONEY 237ML","Code":"30-09","Total Unds":36.0,"Total Cajas":0.857142857142857,"Status":"Alistado","Fecha de Pedido":"2026-06-16","Fecha de Entrega":"2026-06-22","Cliente":"ALMACENES EL REY LIMITADA ","Cod Cliente":"011","Peso Volumetrico":0.0205714285714286},{"OC":"OC-011-1524","Producto":"ROLL ON WILL COUNTY 75ML","Code":"10-01","Total Unds":96.0,"Total Cajas":0.5,"Status":"Alistado","Fecha de Pedido":"2026-06-16","Fecha de Entrega":"2026-06-22","Cliente":"ALMACENES EL REY LIMITADA ","Cod Cliente":"011","Peso Volumetrico":0.0185},{"OC":"OC-011-1524","Producto":"GEL PLASTIMAX 950GR","Code":"20-01","Total Unds":24.0,"Total Cajas":0.8,"Status":"Alistado","Fecha de Pedido":"2026-06-16","Fecha de Entrega":"2026-06-22","Cliente":"ALMACENES EL REY LIMITADA ","Cod Cliente":"011","Peso Volumetrico":0.0296},{"OC":"OC-011-1524","Producto":"TALCO ROSAS 350GR","Code":"50-09","Total Unds":24.0,"Total Cajas":0.444444444444444,"Status":"Alistado","Fecha de Pedido":"2026-06-16","Fecha de Entrega":"2026-06-22","Cliente":"ALMACENES EL REY LIMITADA ","Cod Cliente":"011","Peso Volumetrico":0.0164444444444444},{"OC":"OC-011-1524","Producto":"TALCO WILL COUNTY 375GR","Code":"50-05","Total Unds":30.0,"Total Cajas":0.75,"Status":"Alistado","Fecha de Pedido":"2026-06-16","Fecha de Entrega":"2026-06-22","Cliente":"ALMACENES EL REY LIMITADA ","Cod Cliente":"011","Peso Volumetrico":0.02775},{"OC":"OC-011-1525","Producto":"ROLL ON WILL COUNTY 75ML","Code":"10-01","Total Unds":192.0,"Total Cajas":1.0,"Status":"Alistado","Fecha de Pedido":"2026-06-16","Fecha de Entrega":"2026-06-22","Cliente":"ALMACENES EL REY LIMITADA ","Cod Cliente":"011","Peso Volumetrico":0.037},{"OC":"OC-011-1525","Producto":"GEL PLASTIMAX 950GR","Code":"20-01","Total Unds":48.0,"Total Cajas":1.6,"Status":"Alistado","Fecha de Pedido":"2026-06-16","Fecha de Entrega":"2026-06-22","Cliente":"ALMACENES EL REY LIMITADA ","Cod Cliente":"011","Peso Volumetrico":0.0592},{"OC":"OC-011-1525","Producto":"TALCO ROSAS 350GR","Code":"50-09","Total Unds":72.0,"Total Cajas":1.33333333333333,"Status":"Alistado","Fecha de Pedido":"2026-06-16","Fecha de Entrega":"2026-06-22","Cliente":"ALMACENES EL REY LIMITADA ","Cod Cliente":"011","Peso Volumetrico":0.0493333333333333},{"OC":"OC-011-1525","Producto":"TALCO WILL COUNTY 375GR","Code":"50-05","Total Unds":60.0,"Total Cajas":1.5,"Status":"Alistado","Fecha de Pedido":"2026-06-16","Fecha de Entrega":"2026-06-22","Cliente":"ALMACENES EL REY LIMITADA ","Cod Cliente":"011","Peso Volumetrico":0.0555},{"OC":"OC-011-1526","Producto":"GEL PLASTIMAX 950GR","Code":"20-01","Total Unds":48.0,"Total Cajas":1.6,"Status":"Alistado","Fecha de Pedido":"2026-06-16","Fecha de Entrega":"2026-06-22","Cliente":"ALMACENES EL REY LIMITADA ","Cod Cliente":"011","Peso Volumetrico":0.0592},{"OC":"OC-011-1526","Producto":"TALCO ROSAS 350GR","Code":"50-09","Total Unds":72.0,"Total Cajas":1.33333333333333,"Status":"Alistado","Fecha de Pedido":"2026-06-16","Fecha de Entrega":"2026-06-22","Cliente":"ALMACENES EL REY LIMITADA ","Cod Cliente":"011","Peso Volumetrico":0.0493333333333333},{"OC":"OC-011-1527","Producto":"CREMA SWEET HONEY 237ML","Code":"30-09","Total Unds":72.0,"Total Cajas":1.71428571428571,"Status":"Alistado","Fecha de Pedido":"2026-06-16","Fecha de Entrega":"2026-06-22","Cliente":"ALMACENES EL REY LIMITADA ","Cod Cliente":"011","Peso Volumetrico":0.0411428571428571},{"OC":"OC-011-1527","Producto":"ROLL ON WILL COUNTY 75ML","Code":"10-01","Total Unds":96.0,"Total Cajas":0.5,"Status":"Alistado","Fecha de Pedido":"2026-06-16","Fecha de Entrega":"2026-06-22","Cliente":"ALMACENES EL REY LIMITADA ","Cod Cliente":"011","Peso Volumetrico":0.0185},{"OC":"OC-011-1527","Producto":"TALCO SWEET HONEY 375GR","Code":"50-04","Total Unds":60.0,"Total Cajas":1.5,"Status":"Alistado","Fecha de Pedido":"2026-06-16","Fecha de Entrega":"2026-06-22","Cliente":"ALMACENES EL REY LIMITADA ","Cod Cliente":"011","Peso Volumetrico":0.0555},{"OC":"OC-011-1527","Producto":"TALCO WILL COUNTY 375GR","Code":"50-05","Total Unds":60.0,"Total Cajas":1.5,"Status":"Alistado","Fecha de Pedido":"2026-06-16","Fecha de Entrega":"2026-06-22","Cliente":"ALMACENES EL REY LIMITADA ","Cod Cliente":"011","Peso Volumetrico":0.0555},{"OC":"OC-185-1528","Producto":"ROLL ON SWEET HONEY 75ML","Code":"10-02","Total Unds":192.0,"Total Cajas":1.0,"Status":"Entregado","Fecha de Pedido":"2026-06-17","Fecha de Entrega":"2026-06-23","Cliente":"SUPER MERCADO LUCKY VEN","Cod Cliente":"185","Peso Volumetrico":0.037},{"OC":"OC-185-1528","Producto":"ROLL ON WILL COUNTY 75ML","Code":"10-01","Total Unds":192.0,"Total Cajas":1.0,"Status":"Entregado","Fecha de Pedido":"2026-06-17","Fecha de Entrega":"2026-06-23","Cliente":"SUPER MERCADO LUCKY VEN","Cod Cliente":"185","Peso Volumetrico":0.037},{"OC":"OC-185-1528","Producto":"TALCO BABY GRD 575GR","Code":"50-01","Total Unds":32.0,"Total Cajas":1.0,"Status":"Entregado","Fecha de Pedido":"2026-06-17","Fecha de Entrega":"2026-06-23","Cliente":"SUPER MERCADO LUCKY VEN","Cod Cliente":"185","Peso Volumetrico":0.048},{"OC":"OC-185-1528","Producto":"GEL PLASTIMAX 950GR","Code":"20-01","Total Unds":30.0,"Total Cajas":1.0,"Status":"Entregado","Fecha de Pedido":"2026-06-17","Fecha de Entrega":"2026-06-23","Cliente":"SUPER MERCADO LUCKY VEN","Cod Cliente":"185","Peso Volumetrico":0.037},{"OC":"OC-185-1528","Producto":"SHAMP BABY GRD 946ML","Code":"60-00","Total Unds":32.0,"Total Cajas":2.0,"Status":"Entregado","Fecha de Pedido":"2026-06-17","Fecha de Entrega":"2026-06-23","Cliente":"SUPER MERCADO LUCKY VEN","Cod Cliente":"185","Peso Volumetrico":0.05},{"OC":"OC-185-1528","Producto":"CREMA ALGAMARINA VIT A 437ML","Code":"30-00","Total Unds":54.0,"Total Cajas":1.0,"Status":"Entregado","Fecha de Pedido":"2026-06-17","Fecha de Entrega":"2026-06-23","Cliente":"SUPER MERCADO LUCKY VEN","Cod Cliente":"185","Peso Volumetrico":0.037},{"OC":"OC-185-1528","Producto":"COLONIA EMANUEL 250ML","Code":"40-04","Total Unds":24.0,"Total Cajas":0.6,"Status":"Entregado","Fecha de Pedido":"2026-06-17","Fecha de Entrega":"2026-06-23","Cliente":"SUPER MERCADO LUCKY VEN","Cod Cliente":"185","Peso Volumetrico":0.0144},{"OC":"OC-185-1528","Producto":"TALCO CANDY 375GR","Code":"50-18","Total Unds":12.0,"Total Cajas":0.3,"Status":"Entregado","Fecha de Pedido":"2026-06-17","Fecha de Entrega":"2026-06-23","Cliente":"SUPER MERCADO LUCKY VEN","Cod Cliente":"185","Peso Volumetrico":0.0111},{"OC":"OC-185-1528","Producto":"TALCO FARM AWAY 375GR","Code":"50-06","Total Unds":12.0,"Total Cajas":0.3,"Status":"Entregado","Fecha de Pedido":"2026-06-17","Fecha de Entrega":"2026-06-23","Cliente":"SUPER MERCADO LUCKY VEN","Cod Cliente":"185","Peso Volumetrico":0.0111},{"OC":"OC-185-1528","Producto":"TALCO FIEL 375GR","Code":"50-17","Total Unds":12.0,"Total Cajas":0.3,"Status":"Entregado","Fecha de Pedido":"2026-06-17","Fecha de Entrega":"2026-06-23","Cliente":"SUPER MERCADO LUCKY VEN","Cod Cliente":"185","Peso Volumetrico":0.0111},{"OC":"OC-185-1528","Producto":"TALCO ROSE MEN 375GR","Code":"50-03","Total Unds":12.0,"Total Cajas":0.3,"Status":"Entregado","Fecha de Pedido":"2026-06-17","Fecha de Entrega":"2026-06-23","Cliente":"SUPER MERCADO LUCKY VEN","Cod Cliente":"185","Peso Volumetrico":0.0111},{"OC":"OC-185-1528","Producto":"TALCO SWEET HONEY 375GR","Code":"50-04","Total Unds":12.0,"Total Cajas":0.3,"Status":"Entregado","Fecha de Pedido":"2026-06-17","Fecha de Entrega":"2026-06-23","Cliente":"SUPER MERCADO LUCKY VEN","Cod Cliente":"185","Peso Volumetrico":0.0111},{"OC":"OC-185-1528","Producto":"TALCO WILL COUNTY 375GR","Code":"50-05","Total Unds":12.0,"Total Cajas":0.3,"Status":"Entregado","Fecha de Pedido":"2026-06-17","Fecha de Entrega":"2026-06-23","Cliente":"SUPER MERCADO LUCKY VEN","Cod Cliente":"185","Peso Volumetrico":0.0111},{"OC":"OC-185-1528","Producto":"TALCO INDIRA 375GR","Code":"50-19","Total Unds":12.0,"Total Cajas":0.3,"Status":"Entregado","Fecha de Pedido":"2026-06-17","Fecha de Entrega":"2026-06-23","Cliente":"SUPER MERCADO LUCKY VEN","Cod Cliente":"185","Peso Volumetrico":0.0111},{"OC":"OC-185-1528","Producto":"TALCO ROSAS 350GR","Code":"50-09","Total Unds":18.0,"Total Cajas":0.333333333333333,"Status":"Entregado","Fecha de Pedido":"2026-06-17","Fecha de Entrega":"2026-06-23","Cliente":"SUPER MERCADO LUCKY VEN","Cod Cliente":"185","Peso Volumetrico":0.0123333333333333},{"OC":"OC-004-1529","Producto":"TALCO BABY GRD 575GR","Code":"50-01","Total Unds":32.0,"Total Cajas":1.0,"Status":"Entregado","Fecha de Pedido":"2026-06-17","Fecha de Entrega":"2026-06-23","Cliente":"3-102-872453 SOCIEDAD DE RESPONSABILIDAD LIMITADA SUPER IRAZU","Cod Cliente":"004","Peso Volumetrico":0.048},{"OC":"OC-004-1529","Producto":"TALCO WILL COUNTY 375GR","Code":"50-05","Total Unds":80.0,"Total Cajas":2.0,"Status":"Entregado","Fecha de Pedido":"2026-06-17","Fecha de Entrega":"2026-06-23","Cliente":"3-102-872453 SOCIEDAD DE RESPONSABILIDAD LIMITADA SUPER IRAZU","Cod Cliente":"004","Peso Volumetrico":0.074},{"OC":"OC-004-1529","Producto":"TALCO SWEET HONEY 375GR","Code":"50-04","Total Unds":40.0,"Total Cajas":1.0,"Status":"Entregado","Fecha de Pedido":"2026-06-17","Fecha de Entrega":"2026-06-23","Cliente":"3-102-872453 SOCIEDAD DE RESPONSABILIDAD LIMITADA SUPER IRAZU","Cod Cliente":"004","Peso Volumetrico":0.037},{"OC":"OC-004-1529","Producto":"CREMA ALGAMARINA VIT A 437ML","Code":"30-00","Total Unds":54.0,"Total Cajas":1.0,"Status":"Entregado","Fecha de Pedido":"2026-06-17","Fecha de Entrega":"2026-06-23","Cliente":"3-102-872453 SOCIEDAD DE RESPONSABILIDAD LIMITADA SUPER IRAZU","Cod Cliente":"004","Peso Volumetrico":0.037},{"OC":"OC-004-1529","Producto":"CREMA ALGAMARINA ALOE 437ML","Code":"30-02","Total Unds":54.0,"Total Cajas":1.0,"Status":"Entregado","Fecha de Pedido":"2026-06-17","Fecha de Entrega":"2026-06-23","Cliente":"3-102-872453 SOCIEDAD DE RESPONSABILIDAD LIMITADA SUPER IRAZU","Cod Cliente":"004","Peso Volumetrico":0.037},{"OC":"OC-004-1529","Producto":"CREMA ALGAMARINA VIT E 437ML","Code":"30-01","Total Unds":54.0,"Total Cajas":1.0,"Status":"Entregado","Fecha de Pedido":"2026-06-17","Fecha de Entrega":"2026-06-23","Cliente":"3-102-872453 SOCIEDAD DE RESPONSABILIDAD LIMITADA SUPER IRAZU","Cod Cliente":"004","Peso Volumetrico":0.037},{"OC":"OC-004-1529","Producto":"TRIPACK ROLL ON WILD COUNTY 75ML","Code":"10-52","Total Unds":100.0,"Total Cajas":4.0,"Status":"Entregado","Fecha de Pedido":"2026-06-17","Fecha de Entrega":"2026-06-23","Cliente":"3-102-872453 SOCIEDAD DE RESPONSABILIDAD LIMITADA SUPER IRAZU","Cod Cliente":"004","Peso Volumetrico":0.1},{"OC":"OC-197-1530","Producto":"TALCO WILL COUNTY 375GR","Code":"50-05","Total Unds":40.0,"Total Cajas":1.0,"Status":"Entregado","Fecha de Pedido":"2026-06-17","Fecha de Entrega":"2026-06-23","Cliente":"SUPERMERCADO GRANPOPULAR DE SAN RAFAEL ARRIBA SOCIEDAD DE RESPONSABILIDAD LIMITADA SUPERMERCADO EL POPULAR","Cod Cliente":"197","Peso Volumetrico":0.037},{"OC":"OC-197-1530","Producto":"TALCO CHIEF 375GR","Code":"50-02","Total Unds":40.0,"Total Cajas":1.0,"Status":"Entregado","Fecha de Pedido":"2026-06-17","Fecha de Entrega":"2026-06-23","Cliente":"SUPERMERCADO GRANPOPULAR DE SAN RAFAEL ARRIBA SOCIEDAD DE RESPONSABILIDAD LIMITADA SUPERMERCADO EL POPULAR","Cod Cliente":"197","Peso Volumetrico":0.037},{"OC":"OC-197-1530","Producto":"SHAMP BABY GRD 946ML","Code":"60-00","Total Unds":16.0,"Total Cajas":1.0,"Status":"Entregado","Fecha de Pedido":"2026-06-17","Fecha de Entrega":"2026-06-23","Cliente":"SUPERMERCADO GRANPOPULAR DE SAN RAFAEL ARRIBA SOCIEDAD DE RESPONSABILIDAD LIMITADA SUPERMERCADO EL POPULAR","Cod Cliente":"197","Peso Volumetrico":0.025},{"OC":"OC-197-1530","Producto":"SHAMP BABY PEQ 310ML","Code":"60-01","Total Unds":36.0,"Total Cajas":1.0,"Status":"Entregado","Fecha de Pedido":"2026-06-17","Fecha de Entrega":"2026-06-23","Cliente":"SUPERMERCADO GRANPOPULAR DE SAN RAFAEL ARRIBA SOCIEDAD DE RESPONSABILIDAD LIMITADA SUPERMERCADO EL POPULAR","Cod Cliente":"197","Peso Volumetrico":0.024},{"OC":"OC-197-1530","Producto":"GEL TERAPEUTICO ICE MAX 250GR","Code":"70-00","Total Unds":10.0,"Total Cajas":0.166666666666667,"Status":"Entregado","Fecha de Pedido":"2026-06-17","Fecha de Entrega":"2026-06-23","Cliente":"SUPERMERCADO GRANPOPULAR DE SAN RAFAEL ARRIBA SOCIEDAD DE RESPONSABILIDAD LIMITADA SUPERMERCADO EL POPULAR","Cod Cliente":"197","Peso Volumetrico":0.004},{"OC":"OC-197-1530","Producto":"TALCO SURTIDO AROMAS 150GR","Code":"50-15","Total Unds":100.0,"Total Cajas":1.0,"Status":"Entregado","Fecha de Pedido":"2026-06-17","Fecha de Entrega":"2026-06-23","Cliente":"SUPERMERCADO GRANPOPULAR DE SAN RAFAEL ARRIBA SOCIEDAD DE RESPONSABILIDAD LIMITADA SUPERMERCADO EL POPULAR","Cod Cliente":"197","Peso Volumetrico":0.037},{"OC":"OC-197-1530","Producto":"SHAMP FRACHEL SURTIDO 500ML","Code":"60-07","Total Unds":25.0,"Total Cajas":1.0,"Status":"Entregado","Fecha de Pedido":"2026-06-17","Fecha de Entrega":"2026-06-23","Cliente":"SUPERMERCADO GRANPOPULAR DE SAN RAFAEL ARRIBA SOCIEDAD DE RESPONSABILIDAD LIMITADA SUPERMERCADO EL POPULAR","Cod Cliente":"197","Peso Volumetrico":0.025},{"OC":"OC-238-1531","Producto":"SHAMP BABY GRD 946ML","Code":"60-00","Total Unds":32.0,"Total Cajas":2.0,"Status":"Ingresado","Fecha de Pedido":"2026-06-17","Fecha de Entrega":"2026-06-23","Cliente":"IMPERIO HUIXIAO SOCIEDAD ANONIMA SUPER EL IMPERIO EL ROBLE","Cod Cliente":"238","Peso Volumetrico":0.05},{"OC":"OC-238-1531","Producto":"GEL PLASTIMAX 950GR","Code":"20-01","Total Unds":30.0,"Total Cajas":1.0,"Status":"Ingresado","Fecha de Pedido":"2026-06-17","Fecha de Entrega":"2026-06-23","Cliente":"IMPERIO HUIXIAO SOCIEDAD ANONIMA SUPER EL IMPERIO EL ROBLE","Cod Cliente":"238","Peso Volumetrico":0.037},{"OC":"OC-238-1531","Producto":"GEL PLASTIMAX 250GR","Code":"20-00","Total Unds":60.0,"Total Cajas":1.0,"Status":"Ingresado","Fecha de Pedido":"2026-06-17","Fecha de Entrega":"2026-06-23","Cliente":"IMPERIO HUIXIAO SOCIEDAD ANONIMA SUPER EL IMPERIO EL ROBLE","Cod Cliente":"238","Peso Volumetrico":0.024},{"OC":"OC-214-1531","Producto":"TALCO ROSE MEN 375GR","Code":"50-03","Total Unds":40.0,"Total Cajas":1.0,"Status":"Alistado","Fecha de Pedido":"2026-06-19","Fecha de Entrega":"2026-06-24","Cliente":"WU YEPENG SUPER FAMILIA","Cod Cliente":"214","Peso Volumetrico":0.037},{"OC":"OC-214-1531","Producto":"TALCO CHIEF 375GR","Code":"50-02","Total Unds":40.0,"Total Cajas":1.0,"Status":"Alistado","Fecha de Pedido":"2026-06-19","Fecha de Entrega":"2026-06-24","Cliente":"WU YEPENG SUPER FAMILIA","Cod Cliente":"214","Peso Volumetrico":0.037},{"OC":"OC-214-1531","Producto":"TALCO FARM AWAY 150GR","Code":"50-12","Total Unds":100.0,"Total Cajas":1.0,"Status":"Alistado","Fecha de Pedido":"2026-06-19","Fecha de Entrega":"2026-06-24","Cliente":"WU YEPENG SUPER FAMILIA","Cod Cliente":"214","Peso Volumetrico":0.037},{"OC":"OC-214-1531","Producto":"TALCO WILL COUNTY 375GR","Code":"50-05","Total Unds":40.0,"Total Cajas":1.0,"Status":"Alistado","Fecha de Pedido":"2026-06-19","Fecha de Entrega":"2026-06-24","Cliente":"WU YEPENG SUPER FAMILIA","Cod Cliente":"214","Peso Volumetrico":0.037},{"OC":"OC-214-1531","Producto":"TALCO BABY PEQ 150GR","Code":"50-07","Total Unds":100.0,"Total Cajas":1.0,"Status":"Alistado","Fecha de Pedido":"2026-06-19","Fecha de Entrega":"2026-06-24","Cliente":"WU YEPENG SUPER FAMILIA","Cod Cliente":"214","Peso Volumetrico":0.037},{"OC":"OC-214-1531","Producto":"TALCO SWEET HONEY 375GR","Code":"50-04","Total Unds":40.0,"Total Cajas":1.0,"Status":"Alistado","Fecha de Pedido":"2026-06-19","Fecha de Entrega":"2026-06-24","Cliente":"WU YEPENG SUPER FAMILIA","Cod Cliente":"214","Peso Volumetrico":0.037},{"OC":"OC-214-1531","Producto":"TALCO ROSAS 350GR","Code":"50-09","Total Unds":54.0,"Total Cajas":1.0,"Status":"Alistado","Fecha de Pedido":"2026-06-19","Fecha de Entrega":"2026-06-24","Cliente":"WU YEPENG SUPER FAMILIA","Cod Cliente":"214","Peso Volumetrico":0.037},{"OC":"OC-214-1531","Producto":"TALCO BABY GRD 575GR","Code":"50-01","Total Unds":32.0,"Total Cajas":1.0,"Status":"Alistado","Fecha de Pedido":"2026-06-19","Fecha de Entrega":"2026-06-24","Cliente":"WU YEPENG SUPER FAMILIA","Cod Cliente":"214","Peso Volumetrico":0.048},{"OC":"OC-214-1531","Producto":"ROLL ON SWEET HONEY 75ML","Code":"10-02","Total Unds":192.0,"Total Cajas":1.0,"Status":"Alistado","Fecha de Pedido":"2026-06-19","Fecha de Entrega":"2026-06-24","Cliente":"WU YEPENG SUPER FAMILIA","Cod Cliente":"214","Peso Volumetrico":0.037},{"OC":"OC-214-1531","Producto":"ROLL ON WILL COUNTY 75ML","Code":"10-01","Total Unds":192.0,"Total Cajas":1.0,"Status":"Alistado","Fecha de Pedido":"2026-06-19","Fecha de Entrega":"2026-06-24","Cliente":"WU YEPENG SUPER FAMILIA","Cod Cliente":"214","Peso Volumetrico":0.037},{"OC":"OC-214-1531","Producto":"ROLL ON PARIS DACKAR 75ML","Code":"10-10","Total Unds":192.0,"Total Cajas":1.0,"Status":"Alistado","Fecha de Pedido":"2026-06-19","Fecha de Entrega":"2026-06-24","Cliente":"WU YEPENG SUPER FAMILIA","Cod Cliente":"214","Peso Volumetrico":0.037},{"OC":"OC-214-1531","Producto":"CREMA ALGAMARINA ALOE 437ML","Code":"30-02","Total Unds":54.0,"Total Cajas":1.0,"Status":"Alistado","Fecha de Pedido":"2026-06-19","Fecha de Entrega":"2026-06-24","Cliente":"WU YEPENG SUPER FAMILIA","Cod Cliente":"214","Peso Volumetrico":0.037},{"OC":"OC-214-1531","Producto":"CREMA ALGAMARINA VIT E 437ML","Code":"30-01","Total Unds":54.0,"Total Cajas":1.0,"Status":"Alistado","Fecha de Pedido":"2026-06-19","Fecha de Entrega":"2026-06-24","Cliente":"WU YEPENG SUPER FAMILIA","Cod Cliente":"214","Peso Volumetrico":0.037},{"OC":"OC-214-1531","Producto":"SHAMP BABY GRD 946ML","Code":"60-00","Total Unds":80.0,"Total Cajas":5.0,"Status":"Alistado","Fecha de Pedido":"2026-06-19","Fecha de Entrega":"2026-06-24","Cliente":"WU YEPENG SUPER FAMILIA","Cod Cliente":"214","Peso Volumetrico":0.125},{"OC":"OC-214-1531","Producto":"SHAMP BABY PEQ 310ML","Code":"60-01","Total Unds":144.0,"Total Cajas":4.0,"Status":"Alistado","Fecha de Pedido":"2026-06-19","Fecha de Entrega":"2026-06-24","Cliente":"WU YEPENG SUPER FAMILIA","Cod Cliente":"214","Peso Volumetrico":0.096},{"OC":"OC-214-1531","Producto":"COLONIA EMANUEL 250ML","Code":"40-04","Total Unds":200.0,"Total Cajas":5.0,"Status":"Alistado","Fecha de Pedido":"2026-06-19","Fecha de Entrega":"2026-06-24","Cliente":"WU YEPENG SUPER FAMILIA","Cod Cliente":"214","Peso Volumetrico":0.12},{"OC":"OC-220-1532","Producto":"ROLL ON SWEET HONEY 75ML","Code":"10-02","Total Unds":192.0,"Total Cajas":1.0,"Status":"Alistado","Fecha de Pedido":"2026-06-19","Fecha de Entrega":"2026-06-24","Cliente":"ZHUYANG WU WU SUPER BASICO ALAJUELA","Cod Cliente":"220","Peso Volumetrico":0.037},{"OC":"OC-220-1532","Producto":"ROLL ON IMARY 75ML","Code":"10-12","Total Unds":192.0,"Total Cajas":1.0,"Status":"Alistado","Fecha de Pedido":"2026-06-19","Fecha de Entrega":"2026-06-24","Cliente":"ZHUYANG WU WU SUPER BASICO ALAJUELA","Cod Cliente":"220","Peso Volumetrico":0.037},{"OC":"OC-220-1532","Producto":"ROLL ON WILL COUNTY 75ML","Code":"10-01","Total Unds":192.0,"Total Cajas":1.0,"Status":"Alistado","Fecha de Pedido":"2026-06-19","Fecha de Entrega":"2026-06-24","Cliente":"ZHUYANG WU WU SUPER BASICO ALAJUELA","Cod Cliente":"220","Peso Volumetrico":0.037},{"OC":"OC-220-1532","Producto":"ROLL ON ROSE MEN 75ML","Code":"10-19","Total Unds":192.0,"Total Cajas":1.0,"Status":"Alistado","Fecha de Pedido":"2026-06-19","Fecha de Entrega":"2026-06-24","Cliente":"ZHUYANG WU WU SUPER BASICO ALAJUELA","Cod Cliente":"220","Peso Volumetrico":0.037},{"OC":"OC-220-1532","Producto":"ROLL ON WILL COUNTY 50ML","Code":"10-20","Total Unds":272.0,"Total Cajas":1.0,"Status":"Alistado","Fecha de Pedido":"2026-06-19","Fecha de Entrega":"2026-06-24","Cliente":"ZHUYANG WU WU SUPER BASICO ALAJUELA","Cod Cliente":"220","Peso Volumetrico":0.037},{"OC":"OC-220-1532","Producto":"TALCO BABY GRD 575GR","Code":"50-01","Total Unds":32.0,"Total Cajas":1.0,"Status":"Alistado","Fecha de Pedido":"2026-06-19","Fecha de Entrega":"2026-06-24","Cliente":"ZHUYANG WU WU SUPER BASICO ALAJUELA","Cod Cliente":"220","Peso Volumetrico":0.048},{"OC":"OC-220-1532","Producto":"TALCO BABY PEQ 150GR","Code":"50-07","Total Unds":100.0,"Total Cajas":1.0,"Status":"Alistado","Fecha de Pedido":"2026-06-19","Fecha de Entrega":"2026-06-24","Cliente":"ZHUYANG WU WU SUPER BASICO ALAJUELA","Cod Cliente":"220","Peso Volumetrico":0.037},{"OC":"OC-220-1532","Producto":"TALCO WILL COUNTY 375GR","Code":"50-05","Total Unds":40.0,"Total Cajas":1.0,"Status":"Alistado","Fecha de Pedido":"2026-06-19","Fecha de Entrega":"2026-06-24","Cliente":"ZHUYANG WU WU SUPER BASICO ALAJUELA","Cod Cliente":"220","Peso Volumetrico":0.037},{"OC":"OC-220-1532","Producto":"TALCO CHIEF 375GR","Code":"50-02","Total Unds":40.0,"Total Cajas":1.0,"Status":"Alistado","Fecha de Pedido":"2026-06-19","Fecha de Entrega":"2026-06-24","Cliente":"ZHUYANG WU WU SUPER BASICO ALAJUELA","Cod Cliente":"220","Peso Volumetrico":0.037},{"OC":"OC-220-1532","Producto":"TALCO ROSE MEN 375GR","Code":"50-03","Total Unds":40.0,"Total Cajas":1.0,"Status":"Alistado","Fecha de Pedido":"2026-06-19","Fecha de Entrega":"2026-06-24","Cliente":"ZHUYANG WU WU SUPER BASICO ALAJUELA","Cod Cliente":"220","Peso Volumetrico":0.037},{"OC":"OC-220-1532","Producto":"TALCO INDIRA 375GR","Code":"50-19","Total Unds":40.0,"Total Cajas":1.0,"Status":"Alistado","Fecha de Pedido":"2026-06-19","Fecha de Entrega":"2026-06-24","Cliente":"ZHUYANG WU WU SUPER BASICO ALAJUELA","Cod Cliente":"220","Peso Volumetrico":0.037},{"OC":"OC-220-1532","Producto":"TALCO FIEL 375GR","Code":"50-17","Total Unds":40.0,"Total Cajas":1.0,"Status":"Alistado","Fecha de Pedido":"2026-06-19","Fecha de Entrega":"2026-06-24","Cliente":"ZHUYANG WU WU SUPER BASICO ALAJUELA","Cod Cliente":"220","Peso Volumetrico":0.037},{"OC":"OC-220-1532","Producto":"TALCO FARM AWAY 375GR","Code":"50-06","Total Unds":40.0,"Total Cajas":1.0,"Status":"Alistado","Fecha de Pedido":"2026-06-19","Fecha de Entrega":"2026-06-24","Cliente":"ZHUYANG WU WU SUPER BASICO ALAJUELA","Cod Cliente":"220","Peso Volumetrico":0.037},{"OC":"OC-220-1532","Producto":"TALCO ROSAS 350GR","Code":"50-09","Total Unds":54.0,"Total Cajas":1.0,"Status":"Alistado","Fecha de Pedido":"2026-06-19","Fecha de Entrega":"2026-06-24","Cliente":"ZHUYANG WU WU SUPER BASICO ALAJUELA","Cod Cliente":"220","Peso Volumetrico":0.037},{"OC":"OC-220-1532","Producto":"GEL PLASTIMAX 250GR","Code":"20-00","Total Unds":60.0,"Total Cajas":1.0,"Status":"Alistado","Fecha de Pedido":"2026-06-19","Fecha de Entrega":"2026-06-24","Cliente":"ZHUYANG WU WU SUPER BASICO ALAJUELA","Cod Cliente":"220","Peso Volumetrico":0.024},{"OC":"OC-220-1532","Producto":"SHAMP BABY GRD 946ML","Code":"60-00","Total Unds":16.0,"Total Cajas":1.0,"Status":"Alistado","Fecha de Pedido":"2026-06-19","Fecha de Entrega":"2026-06-24","Cliente":"ZHUYANG WU WU SUPER BASICO ALAJUELA","Cod Cliente":"220","Peso Volumetrico":0.025},{"OC":"OC-220-1532","Producto":"SHAMP BABY PEQ 310ML","Code":"60-01","Total Unds":36.0,"Total Cajas":1.0,"Status":"Alistado","Fecha de Pedido":"2026-06-19","Fecha de Entrega":"2026-06-24","Cliente":"ZHUYANG WU WU SUPER BASICO ALAJUELA","Cod Cliente":"220","Peso Volumetrico":0.024},{"OC":"OC-220-1532","Producto":"CREMA AROMAS SURTIDA 237ML","Code":"30-17","Total Unds":126.0,"Total Cajas":3.0,"Status":"Alistado","Fecha de Pedido":"2026-06-19","Fecha de Entrega":"2026-06-24","Cliente":"ZHUYANG WU WU SUPER BASICO ALAJUELA","Cod Cliente":"220","Peso Volumetrico":0.072},{"OC":"OC-220-1532","Producto":"SHAMP FRACHEL SURTIDO 500ML","Code":"60-07","Total Unds":50.0,"Total Cajas":2.0,"Status":"Alistado","Fecha de Pedido":"2026-06-19","Fecha de Entrega":"2026-06-24","Cliente":"ZHUYANG WU WU SUPER BASICO ALAJUELA","Cod Cliente":"220","Peso Volumetrico":0.05},{"OC":"OC-191-1533","Producto":"SHAMP BABY GRD 946ML","Code":"60-00","Total Unds":240.0,"Total Cajas":15.0,"Status":"Ingresado","Fecha de Pedido":"2026-06-22","Fecha de Entrega":"2026-06-26","Cliente":"Supermercado Calle 8","Cod Cliente":"191","Peso Volumetrico":0.375},{"OC":"OC-191-1533","Producto":"GEL PLASTIMAX 250GR","Code":"20-00","Total Unds":600.0,"Total Cajas":10.0,"Status":"Ingresado","Fecha de Pedido":"2026-06-22","Fecha de Entrega":"2026-06-26","Cliente":"Supermercado Calle 8","Cod Cliente":"191","Peso Volumetrico":0.24},{"OC":"OC-191-1533","Producto":"ROLL ON WILL COUNTY 75ML","Code":"10-01","Total Unds":960.0,"Total Cajas":5.0,"Status":"Ingresado","Fecha de Pedido":"2026-06-22","Fecha de Entrega":"2026-06-26","Cliente":"Supermercado Calle 8","Cod Cliente":"191","Peso Volumetrico":0.185},{"OC":"OC-191-1533","Producto":"ROLL ON ROSE MEN 75ML","Code":"10-19","Total Unds":960.0,"Total Cajas":5.0,"Status":"Ingresado","Fecha de Pedido":"2026-06-22","Fecha de Entrega":"2026-06-26","Cliente":"Supermercado Calle 8","Cod Cliente":"191","Peso Volumetrico":0.185},{"OC":"OC-037-1534","Producto":"GEL PLASTIMAX 950GR","Code":"20-01","Total Unds":24.0,"Total Cajas":0.8,"Status":"Ingresado","Fecha de Pedido":"2026-06-22","Fecha de Entrega":"2026-06-26","Cliente":"CORPORACION COMERCIAL EL EXITO SOCIEDAD ANONIMA","Cod Cliente":"037","Peso Volumetrico":0.0296},{"OC":"OC-037-1534","Producto":"SHAMP BABY GRD 946ML","Code":"60-00","Total Unds":36.0,"Total Cajas":2.25,"Status":"Ingresado","Fecha de Pedido":"2026-06-22","Fecha de Entrega":"2026-06-26","Cliente":"CORPORACION COMERCIAL EL EXITO SOCIEDAD ANONIMA","Cod Cliente":"037","Peso Volumetrico":0.05625},{"OC":"OC-037-1534","Producto":"TALCO BABY GRD 575GR","Code":"50-01","Total Unds":120.0,"Total Cajas":3.75,"Status":"Ingresado","Fecha de Pedido":"2026-06-22","Fecha de Entrega":"2026-06-26","Cliente":"CORPORACION COMERCIAL EL EXITO SOCIEDAD ANONIMA","Cod Cliente":"037","Peso Volumetrico":0.18},{"OC":"OC-037-1534","Producto":"TALCO SWEET HONEY 375GR","Code":"50-04","Total Unds":24.0,"Total Cajas":0.6,"Status":"Ingresado","Fecha de Pedido":"2026-06-22","Fecha de Entrega":"2026-06-26","Cliente":"CORPORACION COMERCIAL EL EXITO SOCIEDAD ANONIMA","Cod Cliente":"037","Peso Volumetrico":0.0222},{"OC":"OC-037-1534","Producto":"ROLL ON SWEET HONEY 75ML","Code":"10-02","Total Unds":24.0,"Total Cajas":0.125,"Status":"Ingresado","Fecha de Pedido":"2026-06-22","Fecha de Entrega":"2026-06-26","Cliente":"CORPORACION COMERCIAL EL EXITO SOCIEDAD ANONIMA","Cod Cliente":"037","Peso Volumetrico":0.004625},{"OC":"OC-505-1535","Producto":"COLONIA EMANUEL 250ML","Code":"40-04","Total Unds":40.0,"Total Cajas":1.0,"Status":"Ingresado","Fecha de Pedido":"2026-06-22","Fecha de Entrega":"2026-06-26","Cliente":"IMPORTADORA PANATICO INTERNACIONAL S.A","Cod Cliente":"505","Peso Volumetrico":0.024},{"OC":"OC-505-1535","Producto":"ACEITE PARA BEBÉ EMANUEL 250ML","Code":"90-00","Total Unds":40.0,"Total Cajas":1.0,"Status":"Ingresado","Fecha de Pedido":"2026-06-22","Fecha de Entrega":"2026-06-26","Cliente":"IMPORTADORA PANATICO INTERNACIONAL S.A","Cod Cliente":"505","Peso Volumetrico":0.024},{"OC":"OC-505-1535","Producto":"CREMA ALGAMARINA ALOE 437ML","Code":"30-02","Total Unds":54.0,"Total Cajas":1.0,"Status":"Ingresado","Fecha de Pedido":"2026-06-22","Fecha de Entrega":"2026-06-26","Cliente":"IMPORTADORA PANATICO INTERNACIONAL S.A","Cod Cliente":"505","Peso Volumetrico":0.037},{"OC":"OC-505-1535","Producto":"CREMA ALGAMARINA VIT A 437ML","Code":"30-00","Total Unds":54.0,"Total Cajas":1.0,"Status":"Ingresado","Fecha de Pedido":"2026-06-22","Fecha de Entrega":"2026-06-26","Cliente":"IMPORTADORA PANATICO INTERNACIONAL S.A","Cod Cliente":"505","Peso Volumetrico":0.037},{"OC":"OC-505-1535","Producto":"CREMA ALGAMARINA VIT E 437ML","Code":"30-01","Total Unds":54.0,"Total Cajas":1.0,"Status":"Ingresado","Fecha de Pedido":"2026-06-22","Fecha de Entrega":"2026-06-26","Cliente":"IMPORTADORA PANATICO INTERNACIONAL S.A","Cod Cliente":"505","Peso Volumetrico":0.037},{"OC":"OC-505-1535","Producto":"CREMA CANDY 237ML","Code":"30-12","Total Unds":42.0,"Total Cajas":1.0,"Status":"Ingresado","Fecha de Pedido":"2026-06-22","Fecha de Entrega":"2026-06-26","Cliente":"IMPORTADORA PANATICO INTERNACIONAL S.A","Cod Cliente":"505","Peso Volumetrico":0.024},{"OC":"OC-505-1535","Producto":"CREMA FARM AWAY 237ML","Code":"30-11","Total Unds":42.0,"Total Cajas":1.0,"Status":"Ingresado","Fecha de Pedido":"2026-06-22","Fecha de Entrega":"2026-06-26","Cliente":"IMPORTADORA PANATICO INTERNACIONAL S.A","Cod Cliente":"505","Peso Volumetrico":0.024},{"OC":"OC-505-1535","Producto":"CREMA FIEL 237ML","Code":"30-14","Total Unds":42.0,"Total Cajas":1.0,"Status":"Ingresado","Fecha de Pedido":"2026-06-22","Fecha de Entrega":"2026-06-26","Cliente":"IMPORTADORA PANATICO INTERNACIONAL S.A","Cod Cliente":"505","Peso Volumetrico":0.024},{"OC":"OC-505-1535","Producto":"CREMA IMARY 237ML","Code":"30-10","Total Unds":42.0,"Total Cajas":1.0,"Status":"Ingresado","Fecha de Pedido":"2026-06-22","Fecha de Entrega":"2026-06-26","Cliente":"IMPORTADORA PANATICO INTERNACIONAL S.A","Cod Cliente":"505","Peso Volumetrico":0.024},{"OC":"OC-505-1535","Producto":"CREMA INDIRA 237ML","Code":"30-13","Total Unds":42.0,"Total Cajas":1.0,"Status":"Ingresado","Fecha de Pedido":"2026-06-22","Fecha de Entrega":"2026-06-26","Cliente":"IMPORTADORA PANATICO INTERNACIONAL S.A","Cod Cliente":"505","Peso Volumetrico":0.024},{"OC":"OC-505-1535","Producto":"CREMA SWEET HONEY 237ML","Code":"30-09","Total Unds":42.0,"Total Cajas":1.0,"Status":"Ingresado","Fecha de Pedido":"2026-06-22","Fecha de Entrega":"2026-06-26","Cliente":"IMPORTADORA PANATICO INTERNACIONAL S.A","Cod Cliente":"505","Peso Volumetrico":0.024},{"OC":"OC-505-1535","Producto":"GEL TERAPEUTICO ICE MAX 250GR","Code":"70-00","Total Unds":30.0,"Total Cajas":0.5,"Status":"Ingresado","Fecha de Pedido":"2026-06-22","Fecha de Entrega":"2026-06-26","Cliente":"IMPORTADORA PANATICO INTERNACIONAL S.A","Cod Cliente":"505","Peso Volumetrico":0.012},{"OC":"OC-505-1535","Producto":"GEL PLASTIMAX 950GR","Code":"20-01","Total Unds":60.0,"Total Cajas":2.0,"Status":"Ingresado","Fecha de Pedido":"2026-06-22","Fecha de Entrega":"2026-06-26","Cliente":"IMPORTADORA PANATICO INTERNACIONAL S.A","Cod Cliente":"505","Peso Volumetrico":0.074},{"OC":"OC-505-1535","Producto":"ROLL ON BLACK SOFT 75ML","Code":"10-03","Total Unds":192.0,"Total Cajas":1.0,"Status":"Ingresado","Fecha de Pedido":"2026-06-22","Fecha de Entrega":"2026-06-26","Cliente":"IMPORTADORA PANATICO INTERNACIONAL S.A","Cod Cliente":"505","Peso Volumetrico":0.037},{"OC":"OC-505-1535","Producto":"ROLL ON SWEET HONEY 75ML","Code":"10-02","Total Unds":192.0,"Total Cajas":1.0,"Status":"Ingresado","Fecha de Pedido":"2026-06-22","Fecha de Entrega":"2026-06-26","Cliente":"IMPORTADORA PANATICO INTERNACIONAL S.A","Cod Cliente":"505","Peso Volumetrico":0.037},{"OC":"OC-505-1535","Producto":"ROLL ON WILL COUNTY 75ML","Code":"10-01","Total Unds":192.0,"Total Cajas":1.0,"Status":"Ingresado","Fecha de Pedido":"2026-06-22","Fecha de Entrega":"2026-06-26","Cliente":"IMPORTADORA PANATICO INTERNACIONAL S.A","Cod Cliente":"505","Peso Volumetrico":0.037},{"OC":"OC-505-1535","Producto":"SHAMP BABY GRD 946ML","Code":"60-00","Total Unds":16.0,"Total Cajas":1.0,"Status":"Ingresado","Fecha de Pedido":"2026-06-22","Fecha de Entrega":"2026-06-26","Cliente":"IMPORTADORA PANATICO INTERNACIONAL S.A","Cod Cliente":"505","Peso Volumetrico":0.025},{"OC":"OC-505-1535","Producto":"SHAMP BABY PEQ 310ML","Code":"60-01","Total Unds":72.0,"Total Cajas":2.0,"Status":"Ingresado","Fecha de Pedido":"2026-06-22","Fecha de Entrega":"2026-06-26","Cliente":"IMPORTADORA PANATICO INTERNACIONAL S.A","Cod Cliente":"505","Peso Volumetrico":0.048},{"OC":"OC-505-1535","Producto":"SHAMP FRACHEL AGUACATE 500ML","Code":"60-02","Total Unds":25.0,"Total Cajas":1.0,"Status":"Ingresado","Fecha de Pedido":"2026-06-22","Fecha de Entrega":"2026-06-26","Cliente":"IMPORTADORA PANATICO INTERNACIONAL S.A","Cod Cliente":"505","Peso Volumetrico":0.025},{"OC":"OC-505-1535","Producto":"SHAMP FRACHEL FRESA 500ML","Code":"60-06","Total Unds":25.0,"Total Cajas":1.0,"Status":"Ingresado","Fecha de Pedido":"2026-06-22","Fecha de Entrega":"2026-06-26","Cliente":"IMPORTADORA PANATICO INTERNACIONAL S.A","Cod Cliente":"505","Peso Volumetrico":0.025},{"OC":"OC-505-1535","Producto":"SHAMP FRACHEL MANZANA 500ML","Code":"60-09","Total Unds":25.0,"Total Cajas":1.0,"Status":"Ingresado","Fecha de Pedido":"2026-06-22","Fecha de Entrega":"2026-06-26","Cliente":"IMPORTADORA PANATICO INTERNACIONAL S.A","Cod Cliente":"505","Peso Volumetrico":0.025},{"OC":"OC-505-1535","Producto":"SHAMP FRACHEL MANZANILLA 500ML","Code":"60-04","Total Unds":25.0,"Total Cajas":1.0,"Status":"Ingresado","Fecha de Pedido":"2026-06-22","Fecha de Entrega":"2026-06-26","Cliente":"IMPORTADORA PANATICO INTERNACIONAL S.A","Cod Cliente":"505","Peso Volumetrico":0.025},{"OC":"OC-505-1535","Producto":"SHAMP FRACHEL MIEL 500ML","Code":"60-05","Total Unds":25.0,"Total Cajas":1.0,"Status":"Ingresado","Fecha de Pedido":"2026-06-22","Fecha de Entrega":"2026-06-26","Cliente":"IMPORTADORA PANATICO INTERNACIONAL S.A","Cod Cliente":"505","Peso Volumetrico":0.025},{"OC":"OC-505-1535","Producto":"SHAMP FRACHEL PEPINO 500ML","Code":"60-10","Total Unds":25.0,"Total Cajas":1.0,"Status":"Ingresado","Fecha de Pedido":"2026-06-22","Fecha de Entrega":"2026-06-26","Cliente":"IMPORTADORA PANATICO INTERNACIONAL S.A","Cod Cliente":"505","Peso Volumetrico":0.025},{"OC":"OC-505-1535","Producto":"SHAMP FRACHEL SABILA 500ML","Code":"60-08","Total Unds":25.0,"Total Cajas":1.0,"Status":"Ingresado","Fecha de Pedido":"2026-06-22","Fecha de Entrega":"2026-06-26","Cliente":"IMPORTADORA PANATICO INTERNACIONAL S.A","Cod Cliente":"505","Peso Volumetrico":0.025},{"OC":"OC-505-1535","Producto":"TALCO BABY GRD 575GR","Code":"50-01","Total Unds":64.0,"Total Cajas":2.0,"Status":"Ingresado","Fecha de Pedido":"2026-06-22","Fecha de Entrega":"2026-06-26","Cliente":"IMPORTADORA PANATICO INTERNACIONAL S.A","Cod Cliente":"505","Peso Volumetrico":0.096},{"OC":"OC-505-1535","Producto":"TALCO CHIEF 375GR","Code":"50-02","Total Unds":40.0,"Total Cajas":1.0,"Status":"Ingresado","Fecha de Pedido":"2026-06-22","Fecha de Entrega":"2026-06-26","Cliente":"IMPORTADORA PANATICO INTERNACIONAL S.A","Cod Cliente":"505","Peso Volumetrico":0.037},{"OC":"OC-505-1535","Producto":"TALCO FARM AWAY 375GR","Code":"50-06","Total Unds":40.0,"Total Cajas":1.0,"Status":"Ingresado","Fecha de Pedido":"2026-06-22","Fecha de Entrega":"2026-06-26","Cliente":"IMPORTADORA PANATICO INTERNACIONAL S.A","Cod Cliente":"505","Peso Volumetrico":0.037},{"OC":"OC-505-1535","Producto":"TALCO FIEL 375GR","Code":"50-17","Total Unds":40.0,"Total Cajas":1.0,"Status":"Ingresado","Fecha de Pedido":"2026-06-22","Fecha de Entrega":"2026-06-26","Cliente":"IMPORTADORA PANATICO INTERNACIONAL S.A","Cod Cliente":"505","Peso Volumetrico":0.037},{"OC":"OC-505-1535","Producto":"TALCO ROSAS 350GR","Code":"50-09","Total Unds":54.0,"Total Cajas":1.0,"Status":"Ingresado","Fecha de Pedido":"2026-06-22","Fecha de Entrega":"2026-06-26","Cliente":"IMPORTADORA PANATICO INTERNACIONAL S.A","Cod Cliente":"505","Peso Volumetrico":0.037},{"OC":"OC-505-1535","Producto":"TALCO ROSE MEN 375GR","Code":"50-03","Total Unds":40.0,"Total Cajas":1.0,"Status":"Ingresado","Fecha de Pedido":"2026-06-22","Fecha de Entrega":"2026-06-26","Cliente":"IMPORTADORA PANATICO INTERNACIONAL S.A","Cod Cliente":"505","Peso Volumetrico":0.037},{"OC":"OC-505-1535","Producto":"TALCO SWEET HONEY 375GR","Code":"50-04","Total Unds":40.0,"Total Cajas":1.0,"Status":"Ingresado","Fecha de Pedido":"2026-06-22","Fecha de Entrega":"2026-06-26","Cliente":"IMPORTADORA PANATICO INTERNACIONAL S.A","Cod Cliente":"505","Peso Volumetrico":0.037},{"OC":"OC-505-1535","Producto":"TALCO WILL COUNTY 375GR","Code":"50-05","Total Unds":40.0,"Total Cajas":1.0,"Status":"Ingresado","Fecha de Pedido":"2026-06-22","Fecha de Entrega":"2026-06-26","Cliente":"IMPORTADORA PANATICO INTERNACIONAL S.A","Cod Cliente":"505","Peso Volumetrico":0.037},{"OC":"OC-505-1535","Producto":"TALCO BABY PEQ 150GR","Code":"50-07","Total Unds":50.0,"Total Cajas":0.5,"Status":"Ingresado","Fecha de Pedido":"2026-06-22","Fecha de Entrega":"2026-06-26","Cliente":"IMPORTADORA PANATICO INTERNACIONAL S.A","Cod Cliente":"505","Peso Volumetrico":0.0185},{"OC":"OC-505-1535","Producto":"TALCO CANDY 150GR","Code":"50-29","Total Unds":50.0,"Total Cajas":0.5,"Status":"Ingresado","Fecha de Pedido":"2026-06-22","Fecha de Entrega":"2026-06-26","Cliente":"IMPORTADORA PANATICO INTERNACIONAL S.A","Cod Cliente":"505","Peso Volumetrico":0.0185},{"OC":"OC-505-1535","Producto":"TALCO CHIEF 150GR","Code":"50-13","Total Unds":50.0,"Total Cajas":0.5,"Status":"Ingresado","Fecha de Pedido":"2026-06-22","Fecha de Entrega":"2026-06-26","Cliente":"IMPORTADORA PANATICO INTERNACIONAL S.A","Cod Cliente":"505","Peso Volumetrico":0.0185},{"OC":"OC-505-1535","Producto":"TALCO FARM AWAY 150GR","Code":"50-12","Total Unds":50.0,"Total Cajas":0.5,"Status":"Ingresado","Fecha de Pedido":"2026-06-22","Fecha de Entrega":"2026-06-26","Cliente":"IMPORTADORA PANATICO INTERNACIONAL S.A","Cod Cliente":"505","Peso Volumetrico":0.0185},{"OC":"OC-505-1535","Producto":"TALCO FIEL 150GR","Code":"50-24","Total Unds":50.0,"Total Cajas":0.5,"Status":"Ingresado","Fecha de Pedido":"2026-06-22","Fecha de Entrega":"2026-06-26","Cliente":"IMPORTADORA PANATICO INTERNACIONAL S.A","Cod Cliente":"505","Peso Volumetrico":0.0185},{"OC":"OC-505-1535","Producto":"TALCO INDIRA 150GR","Code":"50-25","Total Unds":50.0,"Total Cajas":0.5,"Status":"Ingresado","Fecha de Pedido":"2026-06-22","Fecha de Entrega":"2026-06-26","Cliente":"IMPORTADORA PANATICO INTERNACIONAL S.A","Cod Cliente":"505","Peso Volumetrico":0.0185},{"OC":"OC-505-1535","Producto":"TALCO ROSE MEN 150GR","Code":"50-14","Total Unds":50.0,"Total Cajas":0.5,"Status":"Ingresado","Fecha de Pedido":"2026-06-22","Fecha de Entrega":"2026-06-26","Cliente":"IMPORTADORA PANATICO INTERNACIONAL S.A","Cod Cliente":"505","Peso Volumetrico":0.0185},{"OC":"OC-505-1535","Producto":"TALCO SWEET HONEY 150GR","Code":"50-11","Total Unds":50.0,"Total Cajas":0.5,"Status":"Ingresado","Fecha de Pedido":"2026-06-22","Fecha de Entrega":"2026-06-26","Cliente":"IMPORTADORA PANATICO INTERNACIONAL S.A","Cod Cliente":"505","Peso Volumetrico":0.0185},{"OC":"OC-505-1535","Producto":"TALCO WILL COUNTY 150GR","Code":"50-10","Total Unds":50.0,"Total Cajas":0.5,"Status":"Ingresado","Fecha de Pedido":"2026-06-22","Fecha de Entrega":"2026-06-26","Cliente":"IMPORTADORA PANATICO INTERNACIONAL S.A","Cod Cliente":"505","Peso Volumetrico":0.0185},{"OC":"OC-184-1537","Producto":"COLONIA EMANUEL 250ML","Code":"40-04","Total Unds":200.0,"Total Cajas":5.0,"Status":"Ingresado","Fecha de Pedido":"2026-06-23","Fecha de Entrega":"2026-06-29","Cliente":"SUPER MERCADO EL GRAN SOCIO","Cod Cliente":"184","Peso Volumetrico":0.12},{"OC":"OC-184-1537","Producto":"ROLL ON WILL COUNTY 75ML","Code":"10-01","Total Unds":960.0,"Total Cajas":5.0,"Status":"Ingresado","Fecha de Pedido":"2026-06-23","Fecha de Entrega":"2026-06-29","Cliente":"SUPER MERCADO EL GRAN SOCIO","Cod Cliente":"184","Peso Volumetrico":0.185},{"OC":"OC-184-1537","Producto":"ROLL ON ROSE MEN 75ML","Code":"10-19","Total Unds":384.0,"Total Cajas":2.0,"Status":"Ingresado","Fecha de Pedido":"2026-06-23","Fecha de Entrega":"2026-06-29","Cliente":"SUPER MERCADO EL GRAN SOCIO","Cod Cliente":"184","Peso Volumetrico":0.074},{"OC":"OC-184-1537","Producto":"ROLL ON MUSK NARANJA 75ML","Code":"10-07","Total Unds":192.0,"Total Cajas":1.0,"Status":"Ingresado","Fecha de Pedido":"2026-06-23","Fecha de Entrega":"2026-06-29","Cliente":"SUPER MERCADO EL GRAN SOCIO","Cod Cliente":"184","Peso Volumetrico":0.037},{"OC":"OC-184-1537","Producto":"ROLL ON IMARY 75ML","Code":"10-12","Total Unds":192.0,"Total Cajas":1.0,"Status":"Ingresado","Fecha de Pedido":"2026-06-23","Fecha de Entrega":"2026-06-29","Cliente":"SUPER MERCADO EL GRAN SOCIO","Cod Cliente":"184","Peso Volumetrico":0.037},{"OC":"OC-184-1537","Producto":"ROLL ON SWEET HONEY 75ML","Code":"10-02","Total Unds":768.0,"Total Cajas":4.0,"Status":"Ingresado","Fecha de Pedido":"2026-06-23","Fecha de Entrega":"2026-06-29","Cliente":"SUPER MERCADO EL GRAN SOCIO","Cod Cliente":"184","Peso Volumetrico":0.148},{"OC":"OC-184-1537","Producto":"TALCO CHIEF 375GR","Code":"50-02","Total Unds":80.0,"Total Cajas":2.0,"Status":"Ingresado","Fecha de Pedido":"2026-06-23","Fecha de Entrega":"2026-06-29","Cliente":"SUPER MERCADO EL GRAN SOCIO","Cod Cliente":"184","Peso Volumetrico":0.074},{"OC":"OC-184-1537","Producto":"TALCO ROSE MEN 150GR","Code":"50-14","Total Unds":100.0,"Total Cajas":1.0,"Status":"Ingresado","Fecha de Pedido":"2026-06-23","Fecha de Entrega":"2026-06-29","Cliente":"SUPER MERCADO EL GRAN SOCIO","Cod Cliente":"184","Peso Volumetrico":0.037},{"OC":"OC-184-1537","Producto":"TALCO SWEET HONEY 375GR","Code":"50-04","Total Unds":80.0,"Total Cajas":2.0,"Status":"Ingresado","Fecha de Pedido":"2026-06-23","Fecha de Entrega":"2026-06-29","Cliente":"SUPER MERCADO EL GRAN SOCIO","Cod Cliente":"184","Peso Volumetrico":0.074},{"OC":"OC-184-1537","Producto":"TALCO SWEET HONEY 150GR","Code":"50-11","Total Unds":100.0,"Total Cajas":1.0,"Status":"Ingresado","Fecha de Pedido":"2026-06-23","Fecha de Entrega":"2026-06-29","Cliente":"SUPER MERCADO EL GRAN SOCIO","Cod Cliente":"184","Peso Volumetrico":0.037},{"OC":"OC-184-1537","Producto":"TALCO ROSAS 350GR","Code":"50-09","Total Unds":54.0,"Total Cajas":1.0,"Status":"Ingresado","Fecha de Pedido":"2026-06-23","Fecha de Entrega":"2026-06-29","Cliente":"SUPER MERCADO EL GRAN SOCIO","Cod Cliente":"184","Peso Volumetrico":0.037},{"OC":"OC-184-1537","Producto":"GEL PLASTIMAX 950GR","Code":"20-01","Total Unds":150.0,"Total Cajas":5.0,"Status":"Ingresado","Fecha de Pedido":"2026-06-23","Fecha de Entrega":"2026-06-29","Cliente":"SUPER MERCADO EL GRAN SOCIO","Cod Cliente":"184","Peso Volumetrico":0.185},{"OC":"OC-184-1537","Producto":"GEL PLASTIMAX 250GR","Code":"20-00","Total Unds":180.0,"Total Cajas":3.0,"Status":"Ingresado","Fecha de Pedido":"2026-06-23","Fecha de Entrega":"2026-06-29","Cliente":"SUPER MERCADO EL GRAN SOCIO","Cod Cliente":"184","Peso Volumetrico":0.072},{"OC":"OC-184-1537","Producto":"CREMA ALGAMARINA VIT A 437ML","Code":"30-00","Total Unds":108.0,"Total Cajas":2.0,"Status":"Ingresado","Fecha de Pedido":"2026-06-23","Fecha de Entrega":"2026-06-29","Cliente":"SUPER MERCADO EL GRAN SOCIO","Cod Cliente":"184","Peso Volumetrico":0.074},{"OC":"OC-184-1537","Producto":"CREMA ALGAMARINA ALOE 437ML","Code":"30-02","Total Unds":108.0,"Total Cajas":2.0,"Status":"Ingresado","Fecha de Pedido":"2026-06-23","Fecha de Entrega":"2026-06-29","Cliente":"SUPER MERCADO EL GRAN SOCIO","Cod Cliente":"184","Peso Volumetrico":0.074},{"OC":"OC-184-1537","Producto":"CREMA ALGAMARINA VIT E 437ML","Code":"30-01","Total Unds":108.0,"Total Cajas":2.0,"Status":"Ingresado","Fecha de Pedido":"2026-06-23","Fecha de Entrega":"2026-06-29","Cliente":"SUPER MERCADO EL GRAN SOCIO","Cod Cliente":"184","Peso Volumetrico":0.074},{"OC":"OC-184-1537","Producto":"SHAMP BABY GRD 946ML","Code":"60-00","Total Unds":128.0,"Total Cajas":8.0,"Status":"Ingresado","Fecha de Pedido":"2026-06-23","Fecha de Entrega":"2026-06-29","Cliente":"SUPER MERCADO EL GRAN SOCIO","Cod Cliente":"184","Peso Volumetrico":0.2},{"OC":"OC-184-1537","Producto":"SHAMP BABY PEQ 310ML","Code":"60-01","Total Unds":180.0,"Total Cajas":5.0,"Status":"Ingresado","Fecha de Pedido":"2026-06-23","Fecha de Entrega":"2026-06-29","Cliente":"SUPER MERCADO EL GRAN SOCIO","Cod Cliente":"184","Peso Volumetrico":0.12},{"OC":"OC-184-1537","Producto":"SHAMP FRACHEL FRESA 500ML","Code":"60-06","Total Unds":25.0,"Total Cajas":1.0,"Status":"Ingresado","Fecha de Pedido":"2026-06-23","Fecha de Entrega":"2026-06-29","Cliente":"SUPER MERCADO EL GRAN SOCIO","Cod Cliente":"184","Peso Volumetrico":0.025},{"OC":"OC-184-1537","Producto":"SHAMP FRACHEL MANZANA 500ML","Code":"60-09","Total Unds":25.0,"Total Cajas":1.0,"Status":"Ingresado","Fecha de Pedido":"2026-06-23","Fecha de Entrega":"2026-06-29","Cliente":"SUPER MERCADO EL GRAN SOCIO","Cod Cliente":"184","Peso Volumetrico":0.025},{"OC":"OC-184-1537","Producto":"SHAMP FRACHEL SABILA 500ML","Code":"60-08","Total Unds":25.0,"Total Cajas":1.0,"Status":"Ingresado","Fecha de Pedido":"2026-06-23","Fecha de Entrega":"2026-06-29","Cliente":"SUPER MERCADO EL GRAN SOCIO","Cod Cliente":"184","Peso Volumetrico":0.025},{"OC":"OC-184-1537","Producto":"SHAMP FRACHEL AGUACATE 500ML","Code":"60-02","Total Unds":25.0,"Total Cajas":1.0,"Status":"Ingresado","Fecha de Pedido":"2026-06-23","Fecha de Entrega":"2026-06-29","Cliente":"SUPER MERCADO EL GRAN SOCIO","Cod Cliente":"184","Peso Volumetrico":0.025},{"OC":"OC-184-1537","Producto":"SHAMP FRACHEL PEPINO 500ML","Code":"60-10","Total Unds":25.0,"Total Cajas":1.0,"Status":"Ingresado","Fecha de Pedido":"2026-06-23","Fecha de Entrega":"2026-06-29","Cliente":"SUPER MERCADO EL GRAN SOCIO","Cod Cliente":"184","Peso Volumetrico":0.025},{"OC":"OC-184-1537","Producto":"SHAMP FRACHEL MANZANILLA 500ML","Code":"60-04","Total Unds":25.0,"Total Cajas":1.0,"Status":"Ingresado","Fecha de Pedido":"2026-06-23","Fecha de Entrega":"2026-06-29","Cliente":"SUPER MERCADO EL GRAN SOCIO","Cod Cliente":"184","Peso Volumetrico":0.025},{"OC":"OC-184-1537","Producto":"SHAMP FRACHEL MIEL 500ML","Code":"60-05","Total Unds":25.0,"Total Cajas":1.0,"Status":"Ingresado","Fecha de Pedido":"2026-06-23","Fecha de Entrega":"2026-06-29","Cliente":"SUPER MERCADO EL GRAN SOCIO","Cod Cliente":"184","Peso Volumetrico":0.025},{"OC":"OC-026-1538","Producto":"CREMA ALGAMARINA VIT A 437ML","Code":"30-00","Total Unds":54.0,"Total Cajas":1.0,"Status":"Ingresado","Fecha de Pedido":"2026-06-23","Fecha de Entrega":"2026-06-29","Cliente":"CENTRO DE COMPRAS HEREDIA","Cod Cliente":"026","Peso Volumetrico":0.037},{"OC":"OC-026-1538","Producto":"CREMA ALGAMARINA ALOE 437ML","Code":"30-02","Total Unds":54.0,"Total Cajas":1.0,"Status":"Ingresado","Fecha de Pedido":"2026-06-23","Fecha de Entrega":"2026-06-29","Cliente":"CENTRO DE COMPRAS HEREDIA","Cod Cliente":"026","Peso Volumetrico":0.037},{"OC":"OC-026-1538","Producto":"CREMA ALGAMARINA VIT E 437ML","Code":"30-01","Total Unds":54.0,"Total Cajas":1.0,"Status":"Ingresado","Fecha de Pedido":"2026-06-23","Fecha de Entrega":"2026-06-29","Cliente":"CENTRO DE COMPRAS HEREDIA","Cod Cliente":"026","Peso Volumetrico":0.037},{"OC":"OC-026-1538","Producto":"SHAMP FRACHEL AGUACATE 500ML","Code":"60-02","Total Unds":25.0,"Total Cajas":1.0,"Status":"Ingresado","Fecha de Pedido":"2026-06-23","Fecha de Entrega":"2026-06-29","Cliente":"CENTRO DE COMPRAS HEREDIA","Cod Cliente":"026","Peso Volumetrico":0.025},{"OC":"OC-026-1538","Producto":"SHAMP FRACHEL MANZANILLA 500ML","Code":"60-04","Total Unds":25.0,"Total Cajas":1.0,"Status":"Ingresado","Fecha de Pedido":"2026-06-23","Fecha de Entrega":"2026-06-29","Cliente":"CENTRO DE COMPRAS HEREDIA","Cod Cliente":"026","Peso Volumetrico":0.025},{"OC":"OC-026-1538","Producto":"SHAMP FRACHEL MIEL 500ML","Code":"60-05","Total Unds":25.0,"Total Cajas":1.0,"Status":"Ingresado","Fecha de Pedido":"2026-06-23","Fecha de Entrega":"2026-06-29","Cliente":"CENTRO DE COMPRAS HEREDIA","Cod Cliente":"026","Peso Volumetrico":0.025},{"OC":"OC-026-1538","Producto":"SHAMP FRACHEL MANZANA 500ML","Code":"60-09","Total Unds":25.0,"Total Cajas":1.0,"Status":"Ingresado","Fecha de Pedido":"2026-06-23","Fecha de Entrega":"2026-06-29","Cliente":"CENTRO DE COMPRAS HEREDIA","Cod Cliente":"026","Peso Volumetrico":0.025},{"OC":"OC-026-1538","Producto":"TALCO ROSAS 350GR","Code":"50-09","Total Unds":54.0,"Total Cajas":1.0,"Status":"Ingresado","Fecha de Pedido":"2026-06-23","Fecha de Entrega":"2026-06-29","Cliente":"CENTRO DE COMPRAS HEREDIA","Cod Cliente":"026","Peso Volumetrico":0.037},{"OC":"OC-046-1539","Producto":"GEL PLASTIMAX 950GR","Code":"20-01","Total Unds":180.0,"Total Cajas":6.0,"Status":"Ingresado","Fecha de Pedido":"2026-06-23","Fecha de Entrega":"2026-06-29","Cliente":"DETALLES ORION PZ SOCIEDAD ANONIMA","Cod Cliente":"046","Peso Volumetrico":0.222},{"OC":"OC-046-1539","Producto":"ROLL ON SWEET HONEY 50ML","Code":"10-29","Total Unds":1632.0,"Total Cajas":6.0,"Status":"Ingresado","Fecha de Pedido":"2026-06-23","Fecha de Entrega":"2026-06-29","Cliente":"DETALLES ORION PZ SOCIEDAD ANONIMA","Cod Cliente":"046","Peso Volumetrico":0.222},{"OC":"OC-046-1539","Producto":"ROLL ON SWEET HONEY 75ML","Code":"10-02","Total Unds":1152.0,"Total Cajas":6.0,"Status":"Ingresado","Fecha de Pedido":"2026-06-23","Fecha de Entrega":"2026-06-29","Cliente":"DETALLES ORION PZ SOCIEDAD ANONIMA","Cod Cliente":"046","Peso Volumetrico":0.222},{"OC":"OC-046-1539","Producto":"ROLL ON WILL COUNTY 50ML","Code":"10-20","Total Unds":2720.0,"Total Cajas":10.0,"Status":"Ingresado","Fecha de Pedido":"2026-06-23","Fecha de Entrega":"2026-06-29","Cliente":"DETALLES ORION PZ SOCIEDAD ANONIMA","Cod Cliente":"046","Peso Volumetrico":0.37},{"OC":"OC-046-1539","Producto":"ROLL ON WILL COUNTY 75ML","Code":"10-01","Total Unds":1920.0,"Total Cajas":10.0,"Status":"Ingresado","Fecha de Pedido":"2026-06-23","Fecha de Entrega":"2026-06-29","Cliente":"DETALLES ORION PZ SOCIEDAD ANONIMA","Cod Cliente":"046","Peso Volumetrico":0.37},{"OC":"OC-046-1539","Producto":"SHAMP BABY GRD 946ML","Code":"60-00","Total Unds":160.0,"Total Cajas":10.0,"Status":"Ingresado","Fecha de Pedido":"2026-06-23","Fecha de Entrega":"2026-06-29","Cliente":"DETALLES ORION PZ SOCIEDAD ANONIMA","Cod Cliente":"046","Peso Volumetrico":0.25},{"OC":"OC-046-1539","Producto":"TALCO BABY GRD 575GR","Code":"50-01","Total Unds":192.0,"Total Cajas":6.0,"Status":"Ingresado","Fecha de Pedido":"2026-06-23","Fecha de Entrega":"2026-06-29","Cliente":"DETALLES ORION PZ SOCIEDAD ANONIMA","Cod Cliente":"046","Peso Volumetrico":0.288},{"OC":"OC-234-1540","Producto":"CREMA ALGAMARINA ALOE 437ML","Code":"30-02","Total Unds":99.0,"Total Cajas":1.83333333333333,"Status":"Entregado","Fecha de Pedido":"2026-06-23","Fecha de Entrega":"2026-06-29","Cliente":"CORPORACION VADO QUESADA SOCIEDAD ANONIMA ","Cod Cliente":"234","Peso Volumetrico":0.0678333333333333},{"OC":"OC-234-1540","Producto":"CREMA ALGAMARINA VIT A 437ML","Code":"30-00","Total Unds":99.0,"Total Cajas":1.83333333333333,"Status":"Entregado","Fecha de Pedido":"2026-06-23","Fecha de Entrega":"2026-06-29","Cliente":"CORPORACION VADO QUESADA SOCIEDAD ANONIMA ","Cod Cliente":"234","Peso Volumetrico":0.0678333333333333},{"OC":"OC-234-1540","Producto":"CREMA ALGAMARINA VIT E 437ML","Code":"30-01","Total Unds":99.0,"Total Cajas":1.83333333333333,"Status":"Entregado","Fecha de Pedido":"2026-06-23","Fecha de Entrega":"2026-06-29","Cliente":"CORPORACION VADO QUESADA SOCIEDAD ANONIMA ","Cod Cliente":"234","Peso Volumetrico":0.0678333333333333}]}